Workbook

Sheet EMP_1
B1: TOTAL ATIVO | C1: =SUM(C11+C29+C42) -> 0 | E1: =SUM(E11+E29+E42) -> 0 | G1: =SUM(G11+G29+G42) -> 0 | I1: =SUM(I11+I29+I42) -> 0
B2: TOTAL PASSIVO | C2: =C51+C79+C97+C99+C101 -> 0 | E2: =E51+E79+E97+E99+E101 -> 0 | G2: =G51+G79+G97+G99+G101 -> 0 | I2: =I51+I79+I97+I99+I101 -> 0
B3: DIFERENÇA | C3: =C1-C2 -> 0 | E3: =E1-E2 -> 0 | G3: =G1-G2 -> 0 | I3: =I1-I2 -> 0
B5: EMPRESA 1 LTDA
B7: BALANÇO PATRIMONIAL
C8: 44896 | E8: 45261 | G8: 45627 | I8: 45992
B9: ATIVO | C9: R$ MIL | D9: (%) | E9: R$ MIL | F9: (%) | G9: R$ MIL | H9: (%) | I9: R$ MIL | J9: (%)
B11: CIRCULANTE | C11: =SUM(C12:C27) -> 0 | D11: =IF($C$47="ERRO","ERRO",IF($C$47=0,0,C11/$C$47)) -> 0 | E11: =SUM(E12:E27) -> 0 | F11: =IF($E$47="ERRO","ERRO",IF($E$47=0,0,E11/$E$47)) -> 0 | G11: =SUM(G12:G27) -> 0 | H11: =IF($G$47="ERRO","ERRO",IF($G$47=0,0,G11/$G$47)) -> 0 | I11: =SUM(I12:I27) -> 0 | J11: =IF($I$47="ERRO","ERRO",IF($I$47=0,0,I11/$I$47)) -> 0
B12: Caixa e Bancos | D12: =IF($C$47="ERRO","ERRO",IF($C$47=0,0,C12/$C$47)) -> 0 | F12: =IF($E$47="ERRO","ERRO",IF($E$47=0,0,E12/$E$47)) -> 0 | H12: =IF($G$47="ERRO","ERRO",IF($G$47=0,0,G12/$G$47)) -> 0 | J12: =IF($I$47="ERRO","ERRO",IF($I$47=0,0,I12/$I$47)) -> 0
B13: Aplicações Financeiras | D13: =IF($C$47="ERRO","ERRO",IF($C$47=0,0,C13/$C$47)) -> 0 | F13: =IF($E$47="ERRO","ERRO",IF($E$47=0,0,E13/$E$47)) -> 0 | H13: =IF($G$47="ERRO","ERRO",IF($G$47=0,0,G13/$G$47)) -> 0 | J13: =IF($I$47="ERRO","ERRO",IF($I$47=0,0,I13/$I$47)) -> 0
B14: Contas a Receber | D14: =IF($C$47="ERRO","ERRO",IF($C$47=0,0,C14/$C$47)) -> 0 | F14: =IF($E$47="ERRO","ERRO",IF($E$47=0,0,E14/$E$47)) -> 0 | H14: =IF($G$47="ERRO","ERRO",IF($G$47=0,0,G14/$G$47)) -> 0 | J14: =IF($I$47="ERRO","ERRO",IF($I$47=0,0,I14/$I$47)) -> 0
B15: Cooperados | D15: =IF($C$47="ERRO","ERRO",IF($C$47=0,0,C15/$C$47)) -> 0 | F15: =IF($E$47="ERRO","ERRO",IF($E$47=0,0,E15/$E$47)) -> 0 | H15: =IF($G$47="ERRO","ERRO",IF($G$47=0,0,G15/$G$47)) -> 0 | J15: =IF($I$47="ERRO","ERRO",IF($I$47=0,0,I15/$I$47)) -> 0
B16: CVA | D16: =IF($C$47="ERRO","ERRO",IF($C$47=0,0,C16/$C$47)) -> 0 | F16: =IF($E$47="ERRO","ERRO",IF($E$47=0,0,E16/$E$47)) -> 0 | H16: =IF($G$47="ERRO","ERRO",IF($G$47=0,0,G16/$G$47)) -> 0 | J16: =IF($I$47="ERRO","ERRO",IF($I$47=0,0,I16/$I$47)) -> 0
B17: Estoques | D17: =IF($C$47="ERRO","ERRO",IF($C$47=0,0,C17/$C$47)) -> 0 | F17: =IF($E$47="ERRO","ERRO",IF($E$47=0,0,E17/$E$47)) -> 0 | H17: =IF($G$47="ERRO","ERRO",IF($G$47=0,0,G17/$G$47)) -> 0 | J17: =IF($I$47="ERRO","ERRO",IF($I$47=0,0,I17/$I$47)) -> 0
B18: Adiant. a Fornecedores | D18: =IF($C$47="ERRO","ERRO",IF($C$47=0,0,C18/$C$47)) -> 0 | F18: =IF($E$47="ERRO","ERRO",IF($E$47=0,0,E18/$E$47)) -> 0 | H18: =IF($G$47="ERRO","ERRO",IF($G$47=0,0,G18/$G$47)) -> 0 | J18: =IF($I$47="ERRO","ERRO",IF($I$47=0,0,I18/$I$47)) -> 0
B19: Créditos a Fumicultores | D19: =IF($C$47="ERRO","ERRO",IF($C$47=0,0,C19/$C$47)) -> 0 | F19: =IF($E$47="ERRO","ERRO",IF($E$47=0,0,E19/$E$47)) -> 0 | H19: =IF($G$47="ERRO","ERRO",IF($G$47=0,0,G19/$G$47)) -> 0 | J19: =IF($I$47="ERRO","ERRO",IF($I$47=0,0,I19/$I$47)) -> 0
B20: Despesas Antecipadas | D20: =IF($C$47="ERRO","ERRO",IF($C$47=0,0,C20/$C$47)) -> 0 | F20: =IF($E$47="ERRO","ERRO",IF($E$47=0,0,E20/$E$47)) -> 0 | H20: =IF($G$47="ERRO","ERRO",IF($G$47=0,0,G20/$G$47)) -> 0 | J20: =IF($I$47="ERRO","ERRO",IF($I$47=0,0,I20/$I$47)) -> 0
B21: Impostos a Recuperar | D21: =IF($C$47="ERRO","ERRO",IF($C$47=0,0,C21/$C$47)) -> 0 | F21: =IF($E$47="ERRO","ERRO",IF($E$47=0,0,E21/$E$47)) -> 0 | H21: =IF($G$47="ERRO","ERRO",IF($G$47=0,0,G21/$G$47)) -> 0 | J21: =IF($I$47="ERRO","ERRO",IF($I$47=0,0,I21/$I$47)) -> 0
B22: Dividendos a Receber | D22: =IF($C$47="ERRO","ERRO",IF($C$47=0,0,C22/$C$47)) -> 0 | F22: =IF($E$47="ERRO","ERRO",IF($E$47=0,0,E22/$E$47)) -> 0 | H22: =IF($G$47="ERRO","ERRO",IF($G$47=0,0,G22/$G$47)) -> 0 | J22: =IF($I$47="ERRO","ERRO",IF($I$47=0,0,I22/$I$47)) -> 0
B23: Imposto Diferido | D23: =IF($C$47="ERRO","ERRO",IF($C$47=0,0,C23/$C$47)) -> 0 | F23: =IF($E$47="ERRO","ERRO",IF($E$47=0,0,E23/$E$47)) -> 0 | H23: =IF($G$47="ERRO","ERRO",IF($G$47=0,0,G23/$G$47)) -> 0 | J23: =IF($I$47="ERRO","ERRO",IF($I$47=0,0,I23/$I$47)) -> 0
... B27: Outros Nao Operac. | D27: =IF($C$47="ERRO","ERRO",IF($C$47=0,0,C27/$C$47)) -> 0 | F27: =IF($E$47="ERRO","ERRO",IF($E$47=0,0,E27/$E$47)) -> 0 | H27: =IF($G$47="ERRO","ERRO",IF($G$47=0,0,G27/$G$47)) -> 0 | J27: =IF($I$47="ERRO","ERRO",IF($I$47=0,0,I27/$I$47)) -> 0
B29: REALIZ. L.P. | C29: =SUM(C30:C40) -> 0 | D29: =IF($C$47="ERRO","ERRO",IF($C$47=0,0,C29/$C$47)) -> 0 | E29: =SUM(E30:E40) -> 0 | F29: =IF($E$47="ERRO","ERRO",IF($E$47=0,0,E29/$E$47)) -> 0 | G29: =SUM(G30:G40) -> 0 | H29: =IF($G$47="ERRO","ERRO",IF($G$47=0,0,G29/$G$47)) -> 0 | I29: =SUM(I30:I40) -> 0 | J29: =IF($I$47="ERRO","ERRO",IF($I$47=0,0,I29/$I$47)) -> 0
B30: Contas a Receber | D30: =IF($C$47="ERRO","ERRO",IF($C$47=0,0,C30/$C$47)) -> 0 | F30: =IF($E$47="ERRO","ERRO",IF($E$47=0,0,E30/$E$47)) -> 0 | H30: =IF($G$47="ERRO","ERRO",IF($G$47=0,0,G30/$G$47)) -> 0 | J30: =IF($I$47="ERRO","ERRO",IF($I$47=0,0,I30/$I$47)) -> 0
B31: Cooperados | D31: =IF($C$47="ERRO","ERRO",IF($C$47=0,0,C31/$C$47)) -> 0 | F31: =IF($E$47="ERRO","ERRO",IF($E$47=0,0,E31/$E$47)) -> 0 | H31: =IF($G$47="ERRO","ERRO",IF($G$47=0,0,G31/$G$47)) -> 0 | J31: =IF($I$47="ERRO","ERRO",IF($I$47=0,0,I31/$I$47)) -> 0
B32: C/C Coligadas/Acionistas | D32: =IF($C$47="ERRO","ERRO",IF($C$47=0,0,C32/$C$47)) -> 0 | F32: =IF($E$47="ERRO","ERRO",IF($E$47=0,0,E32/$E$47)) -> 0 | H32: =IF($G$47="ERRO","ERRO",IF($G$47=0,0,G32/$G$47)) -> 0 | J32: =IF($I$47="ERRO","ERRO",IF($I$47=0,0,I32/$I$47)) -> 0
B33: Depósitos Judiciais | D33: =IF($C$47="ERRO","ERRO",IF($C$47=0,0,C33/$C$47)) -> 0 | F33: =IF($E$47="ERRO","ERRO",IF($E$47=0,0,E33/$E$47)) -> 0 | H33: =IF($G$47="ERRO","ERRO",IF($G$47=0,0,G33/$G$47)) -> 0 | J33: =IF($I$47="ERRO","ERRO",IF($I$47=0,0,I33/$I$47)) -> 0
B34: Imposto Diferido | D34: =IF($C$47="ERRO","ERRO",IF($C$47=0,0,C34/$C$47)) -> 0 | F34: =IF($E$47="ERRO","ERRO",IF($E$47=0,0,E34/$E$47)) -> 0 | H34: =IF($G$47="ERRO","ERRO",IF($G$47=0,0,G34/$G$47)) -> 0 | J34: =IF($I$47="ERRO","ERRO",IF($I$47=0,0,I34/$I$47)) -> 0
B35: Créditos a Fumicultores | D35: =IF($C$47="ERRO","ERRO",IF($C$47=0,0,C35/$C$47)) -> 0 | F35: =IF($E$47="ERRO","ERRO",IF($E$47=0,0,E35/$E$47)) -> 0 | H35: =IF($G$47="ERRO","ERRO",IF($G$47=0,0,G35/$G$47)) -> 0 | J35: =IF($I$47="ERRO","ERRO",IF($I$47=0,0,I35/$I$47)) -> 0
B36: CTN´s | D36: =IF($C$47="ERRO","ERRO",IF($C$47=0,0,C36/$C$47)) -> 0 | F36: =IF($E$47="ERRO","ERRO",IF($E$47=0,0,E36/$E$47)) -> 0 | H36: =IF($G$47="ERRO","ERRO",IF($G$47=0,0,G36/$G$47)) -> 0 | J36: =IF($I$47="ERRO","ERRO",IF($I$47=0,0,I36/$I$47)) -> 0
B37: Outros Operac. | D37: =IF($C$47="ERRO","ERRO",IF($C$47=0,0,C37/$C$47)) -> 0 | F37: =IF($E$47="ERRO","ERRO",IF($E$47=0,0,E37/$E$47)) -> 0 | H37: =IF($G$47="ERRO","ERRO",IF($G$47=0,0,G37/$G$47)) -> 0 | J37: =IF($I$47="ERRO","ERRO",IF($I$47=0,0,I37/$I$47)) -> 0
B38: Outros Operac. | D38: =IF($C$47="ERRO","ERRO",IF($C$47=0,0,C38/$C$47)) -> 0 | F38: =IF($E$47="ERRO","ERRO",IF($E$47=0,0,E38/$E$47)) -> 0 | H38: =IF($G$47="ERRO","ERRO",IF($G$47=0,0,G38/$G$47)) -> 0 | J38: =IF($I$47="ERRO","ERRO",IF($I$47=0,0,I38/$I$47)) -> 0
B39: Outros Nao Operac. | D39: =IF($C$47="ERRO","ERRO",IF($C$47=0,0,C39/$C$47)) -> 0 | F39: =IF($E$47="ERRO","ERRO",IF($E$47=0,0,E39/$E$47)) -> 0 | H39: =IF($G$47="ERRO","ERRO",IF($G$47=0,0,G39/$G$47)) -> 0 | J39: =IF($I$47="ERRO","ERRO",IF($I$47=0,0,I39/$I$47)) -> 0
B40: Outros Nao Operac. | D40: =IF($C$47="ERRO","ERRO",IF($C$47=0,0,C40/$C$47)) -> 0 | F40: =IF($E$47="ERRO","ERRO",IF($E$47=0,0,E40/$E$47)) -> 0 | H40: =IF($G$47="ERRO","ERRO",IF($G$47=0,0,G40/$G$47)) -> 0 | J40: =IF($I$47="ERRO","ERRO",IF($I$47=0,0,I40/$I$47)) -> 0
B42: PERMANENTE | C42: =SUM(C43:C45) -> 0 | D42: =IF($C$47="ERRO","ERRO",IF($C$47=0,0,C42/$C$47)) -> 0 | E42: =SUM(E43:E45) -> 0 | F42: =IF($E$47="ERRO","ERRO",IF($E$47=0,0,E42/$E$47)) -> 0 | G42: =SUM(G43:G45) -> 0 | H42: =IF($G$47="ERRO","ERRO",IF($G$47=0,0,G42/$G$47)) -> 0 | I42: =SUM(I43:I45) -> 0 | J42: =IF($I$47="ERRO","ERRO",IF($I$47=0,0,I42/$I$47)) -> 0
B43: Imobilizado Técnico | D43: =IF($C$47="ERRO","ERRO",IF($C$47=0,0,C43/$C$47)) -> 0 | F43: =IF($E$47="ERRO","ERRO",IF($E$47=0,0,E43/$E$47)) -> 0 | H43: =IF($G$47="ERRO","ERRO",IF($G$47=0,0,G43/$G$47)) -> 0 | J43: =IF($I$47="ERRO","ERRO",IF($I$47=0,0,I43/$I$47)) -> 0
B44: Investimentos | D44: =IF($C$47="ERRO","ERRO",IF($C$47=0,0,C44/$C$47)) -> 0 | F44: =IF($E$47="ERRO","ERRO",IF($E$47=0,0,E44/$E$47)) -> 0 | H44: =IF($G$47="ERRO","ERRO",IF($G$47=0,0,G44/$G$47)) -> 0 | J44: =IF($I$47="ERRO","ERRO",IF($I$47=0,0,I44/$I$47)) -> 0
B45: Diferido/Intangível | D45: =IF($C$47="ERRO","ERRO",IF($C$47=0,0,C45/$C$47)) -> 0 | F45: =IF($E$47="ERRO","ERRO",IF($E$47=0,0,E45/$E$47)) -> 0 | H45: =IF($G$47="ERRO","ERRO",IF($G$47=0,0,G45/$G$47)) -> 0 | J45: =IF($I$47="ERRO","ERRO",IF($I$47=0,0,I45/$I$47)) -> 0
B47: TOTAL | C47: =IF(OR(C11+C29+C42-C51-C79-C97-C99-C101>1,C11+C29+C42-C51-C79-C97-C99-C101<-1),"ERRO",C11+C29+C42) -> 0 | D47: =IF($C$47="ERRO","ERRO",IF($C$47=0,0,C47/$C$47)) -> 0 | E47: =IF(OR(E11+E29+E42-E51-E79-E97-E99-E101>1,E11+E29+E42-E51-E79-E97-E99-E101<-1),"ERRO",E11+E29+E42) -> 0 | F47: =IF($E$47="ERRO","ERRO",IF($E$47=0,0,E47/$E$47)) -> 0 | G47: =IF(OR(G11+G29+G42-G51-G79-G97-G99-G101>1,G11+G29+G42-G51-G79-G97-G99-G101<-1),"ERRO",G11+G29+G42) -> 0 | H47: =IF($G$47="ERRO","ERRO",IF($G$47=0,0,G47/$G$47)) -> 0 | I47: =IF(OR(I11+I29+I42-I51-I79-I97-I99-I101>1,I11+I29+I42-I51-I79-I97-I99-I101<-1),"ERRO",I11+I29+I42) -> 0 | J47: =IF($I$47="ERRO","ERRO",IF($I$47=0,0,I47/$I$47)) -> 0
B49: PASSIVO | C49: R$ MIL | D49: (%) | E49: R$ MIL | F49: (%) | G49: R$ MIL | H49: (%) | I49: R$ MIL | J49: (%)
B51: CIRCULANTE | C51: =SUM(C52:C77) -> 0 | D51: =IF($C$47="ERRO","ERRO",IF($C$47=0,0,C51/$C$47)) -> 0 | E51: =SUM(E52:E77) -> 0 | F51: =IF($E$47="ERRO","ERRO",IF($E$47=0,0,E51/$E$47)) -> 0 | G51: =SUM(G52:G77) -> 0 | H51: =IF($G$47="ERRO","ERRO",IF($G$47=0,0,G51/$G$47)) -> 0 | I51: =SUM(I52:I77) -> 0 | J51: =IF($I$47="ERRO","ERRO",IF($I$47=0,0,I51/$I$47)) -> 0
B52: Fornecedores Nacionais | D52: =IF($C$47="ERRO","ERRO",IF($C$47=0,0,C52/$C$47)) -> 0 | F52: =IF($E$47="ERRO","ERRO",IF($E$47=0,0,E52/$E$47)) -> 0 | H52: =IF($G$47="ERRO","ERRO",IF($G$47=0,0,G52/$G$47)) -> 0 | J52: =IF($I$47="ERRO","ERRO",IF($I$47=0,0,I52/$I$47)) -> 0
B53: Fornecedores Estrangeiros | D53: =IF($C$47="ERRO","ERRO",IF($C$47=0,0,C53/$C$47)) -> 0 | F53: =IF($E$47="ERRO","ERRO",IF($E$47=0,0,E53/$E$47)) -> 0 | H53: =IF($G$47="ERRO","ERRO",IF($G$47=0,0,G53/$G$47)) -> 0 | J53: =IF($I$47="ERRO","ERRO",IF($I$47=0,0,I53/$I$47)) -> 0
B54: Empréstimos Bancários | D54: =IF($C$47="ERRO","ERRO",IF($C$47=0,0,C54/$C$47)) -> 0 | F54: =IF($E$47="ERRO","ERRO",IF($E$47=0,0,E54/$E$47)) -> 0 | H54: =IF($G$47="ERRO","ERRO",IF($G$47=0,0,G54/$G$47)) -> 0 | J54: =IF($I$47="ERRO","ERRO",IF($I$47=0,0,I54/$I$47)) -> 0
B55: Financiamentos Operacionais | D55: =IF($C$47="ERRO","ERRO",IF($C$47=0,0,C55/$C$47)) -> 0 | F55: =IF($E$47="ERRO","ERRO",IF($E$47=0,0,E55/$E$47)) -> 0 | H55: =IF($G$47="ERRO","ERRO",IF($G$47=0,0,G55/$G$47)) -> 0 | J55: =IF($I$47="ERRO","ERRO",IF($I$47=0,0,I55/$I$47)) -> 0
B56: Financiamentos c/ Tradings | D56: =IF($C$47="ERRO","ERRO",IF($C$47=0,0,C56/$C$47)) -> 0 | F56: =IF($E$47="ERRO","ERRO",IF($E$47=0,0,E56/$E$47)) -> 0 | H56: =IF($G$47="ERRO","ERRO",IF($G$47=0,0,G56/$G$47)) -> 0 | J56: =IF($I$47="ERRO","ERRO",IF($I$47=0,0,I56/$I$47)) -> 0
B57: Parcelas Correntes Financ. L.P. | D57: =IF($C$47="ERRO","ERRO",IF($C$47=0,0,C57/$C$47)) -> 0 | F57: =IF($E$47="ERRO","ERRO",IF($E$47=0,0,E57/$E$47)) -> 0 | H57: =IF($G$47="ERRO","ERRO",IF($G$47=0,0,G57/$G$47)) -> 0 | J57: =IF($I$47="ERRO","ERRO",IF($I$47=0,0,I57/$I$47)) -> 0
B58: Debêntures | D58: =IF($C$47="ERRO","ERRO",IF($C$47=0,0,C58/$C$47)) -> 0 | F58: =IF($E$47="ERRO","ERRO",IF($E$47=0,0,E58/$E$47)) -> 0 | H58: =IF($G$47="ERRO","ERRO",IF($G$47=0,0,G58/$G$47)) -> 0 | J58: =IF($I$47="ERRO","ERRO",IF($I$47=0,0,I58/$I$47)) -> 0
B59: Swap | D59: =IF($C$47="ERRO","ERRO",IF($C$47=0,0,C59/$C$47)) -> 0 | F59: =IF($E$47="ERRO","ERRO",IF($E$47=0,0,E59/$E$47)) -> 0 | H59: =IF($G$47="ERRO","ERRO",IF($G$47=0,0,G59/$G$47)) -> 0 | J59: =IF($I$47="ERRO","ERRO",IF($I$47=0,0,I59/$I$47)) -> 0
B60: Securitização | D60: =IF($C$47="ERRO","ERRO",IF($C$47=0,0,C60/$C$47)) -> 0 | F60: =IF($E$47="ERRO","ERRO",IF($E$47=0,0,E60/$E$47)) -> 0 | H60: =IF($G$47="ERRO","ERRO",IF($G$47=0,0,G60/$G$47)) -> 0 | J60: =IF($I$47="ERRO","ERRO",IF($I$47=0,0,I60/$I$47)) -> 0
B61: Leasing | D61: =IF($C$47="ERRO","ERRO",IF($C$47=0,0,C61/$C$47)) -> 0 | F61: =IF($E$47="ERRO","ERRO",IF($E$47=0,0,E61/$E$47)) -> 0 | H61: =IF($G$47="ERRO","ERRO",IF($G$47=0,0,G61/$G$47)) -> 0 | J61: =IF($I$47="ERRO","ERRO",IF($I$47=0,0,I61/$I$47)) -> 0
B62: Salários e Encargos | D62: =IF($C$47="ERRO","ERRO",IF($C$47=0,0,C62/$C$47)) -> 0 | F62: =IF($E$47="ERRO","ERRO",IF($E$47=0,0,E62/$E$47)) -> 0 | H62: =IF($G$47="ERRO","ERRO",IF($G$47=0,0,G62/$G$47)) -> 0 | J62: =IF($I$47="ERRO","ERRO",IF($I$47=0,0,I62/$I$47)) -> 0
B63: Tributos e Obrigações Fiscais | D63: =IF($C$47="ERRO","ERRO",IF($C$47=0,0,C63/$C$47)) -> 0 | F63: =IF($E$47="ERRO","ERRO",IF($E$47=0,0,E63/$E$47)) -> 0 | H63: =IF($G$47="ERRO","ERRO",IF($G$47=0,0,G63/$G$47)) -> 0 | J63: =IF($I$47="ERRO","ERRO",IF($I$47=0,0,I63/$I$47)) -> 0
... B77: Outros Nao Operac. | D77: =IF($C$47="ERRO","ERRO",IF($C$47=0,0,C77/$C$47)) -> 0 | F77: =IF($E$47="ERRO","ERRO",IF($E$47=0,0,E77/$E$47)) -> 0 | H77: =IF($G$47="ERRO","ERRO",IF($G$47=0,0,G77/$G$47)) -> 0 | J77: =IF($I$47="ERRO","ERRO",IF($I$47=0,0,I77/$I$47)) -> 0
B79: EXIGÍVEL L.P. | C79: =SUM(C80:C95) -> 0 | D79: =IF($C$47="ERRO","ERRO",IF($C$47=0,0,C79/$C$47)) -> 0 | E79: =SUM(E80:E95) -> 0 | F79: =IF($E$47="ERRO","ERRO",IF($E$47=0,0,E79/$E$47)) -> 0 | G79: =SUM(G80:G95) -> 0 | H79: =IF($G$47="ERRO","ERRO",IF($G$47=0,0,G79/$G$47)) -> 0 | I79: =SUM(I80:I95) -> 0 | J79: =IF($I$47="ERRO","ERRO",IF($I$47=0,0,I79/$I$47)) -> 0
B80: Empréstimos e Financiamentos | D80: =IF($C$47="ERRO","ERRO",IF($C$47=0,0,C80/$C$47)) -> 0 | F80: =IF($E$47="ERRO","ERRO",IF($E$47=0,0,E80/$E$47)) -> 0 | H80: =IF($G$47="ERRO","ERRO",IF($G$47=0,0,G80/$G$47)) -> 0 | J80: =IF($I$47="ERRO","ERRO",IF($I$47=0,0,I80/$I$47)) -> 0
B81: Debêntures | D81: =IF($C$47="ERRO","ERRO",IF($C$47=0,0,C81/$C$47)) -> 0 | F81: =IF($E$47="ERRO","ERRO",IF($E$47=0,0,E81/$E$47)) -> 0 | H81: =IF($G$47="ERRO","ERRO",IF($G$47=0,0,G81/$G$47)) -> 0 | J81: =IF($I$47="ERRO","ERRO",IF($I$47=0,0,I81/$I$47)) -> 0
B82: Leasing | D82: =IF($C$47="ERRO","ERRO",IF($C$47=0,0,C82/$C$47)) -> 0 | F82: =IF($E$47="ERRO","ERRO",IF($E$47=0,0,E82/$E$47)) -> 0 | H82: =IF($G$47="ERRO","ERRO",IF($G$47=0,0,G82/$G$47)) -> 0 | J82: =IF($I$47="ERRO","ERRO",IF($I$47=0,0,I82/$I$47)) -> 0
B83: Financiamentos c/ Tradings | D83: =IF($C$47="ERRO","ERRO",IF($C$47=0,0,C83/$C$47)) -> 0 | F83: =IF($E$47="ERRO","ERRO",IF($E$47=0,0,E83/$E$47)) -> 0 | H83: =IF($G$47="ERRO","ERRO",IF($G$47=0,0,G83/$G$47)) -> 0 | J83: =IF($I$47="ERRO","ERRO",IF($I$47=0,0,I83/$I$47)) -> 0
B84: Securitização | D84: =IF($C$47="ERRO","ERRO",IF($C$47=0,0,C84/$C$47)) -> 0 | F84: =IF($E$47="ERRO","ERRO",IF($E$47=0,0,E84/$E$47)) -> 0 | H84: =IF($G$47="ERRO","ERRO",IF($G$47=0,0,G84/$G$47)) -> 0 | J84: =IF($I$47="ERRO","ERRO",IF($I$47=0,0,I84/$I$47)) -> 0
B85: Custo Orçado | D85: =IF($C$47="ERRO","ERRO",IF($C$47=0,0,C85/$C$47)) -> 0 | F85: =IF($E$47="ERRO","ERRO",IF($E$47=0,0,E85/$E$47)) -> 0 | H85: =IF($G$47="ERRO","ERRO",IF($G$47=0,0,G85/$G$47)) -> 0 | J85: =IF($I$47="ERRO","ERRO",IF($I$47=0,0,I85/$I$47)) -> 0
B86: Terrenos | D86: =IF($C$47="ERRO","ERRO",IF($C$47=0,0,C86/$C$47)) -> 0 | F86: =IF($E$47="ERRO","ERRO",IF($E$47=0,0,E86/$E$47)) -> 0 | H86: =IF($G$47="ERRO","ERRO",IF($G$47=0,0,G86/$G$47)) -> 0 | J86: =IF($I$47="ERRO","ERRO",IF($I$47=0,0,I86/$I$47)) -> 0
B87: Outorga | D87: =IF($C$47="ERRO","ERRO",IF($C$47=0,0,C87/$C$47)) -> 0 | F87: =IF($E$47="ERRO","ERRO",IF($E$47=0,0,E87/$E$47)) -> 0 | H87: =IF($G$47="ERRO","ERRO",IF($G$47=0,0,G87/$G$47)) -> 0 | J87: =IF($I$47="ERRO","ERRO",IF($I$47=0,0,I87/$I$47)) -> 0
B88: Compromissos Consorciados | D88: =IF($C$47="ERRO","ERRO",IF($C$47=0,0,C88/$C$47)) -> 0 | F88: =IF($E$47="ERRO","ERRO",IF($E$47=0,0,E88/$E$47)) -> 0 | H88: =IF($G$47="ERRO","ERRO",IF($G$47=0,0,G88/$G$47)) -> 0 | J88: =IF($I$47="ERRO","ERRO",IF($I$47=0,0,I88/$I$47)) -> 0
B89: Plano de Previdênciário | D89: =IF($C$47="ERRO","ERRO",IF($C$47=0,0,C89/$C$47)) -> 0 | F89: =IF($E$47="ERRO","ERRO",IF($E$47=0,0,E89/$E$47)) -> 0 | H89: =IF($G$47="ERRO","ERRO",IF($G$47=0,0,G89/$G$47)) -> 0 | J89: =IF($I$47="ERRO","ERRO",IF($I$47=0,0,I89/$I$47)) -> 0
B90: Dividendos a pagar | D90: =IF($C$47="ERRO","ERRO",IF($C$47=0,0,C90/$C$47)) -> 0 | F90: =IF($E$47="ERRO","ERRO",IF($E$47=0,0,E90/$E$47)) -> 0 | H90: =IF($G$47="ERRO","ERRO",IF($G$47=0,0,G90/$G$47)) -> 0 | J90: =IF($I$47="ERRO","ERRO",IF($I$47=0,0,I90/$I$47)) -> 0
B91: Provisão para Contingência | D91: =IF($C$47="ERRO","ERRO",IF($C$47=0,0,C91/$C$47)) -> 0 | F91: =IF($E$47="ERRO","ERRO",IF($E$47=0,0,E91/$E$47)) -> 0 | H91: =IF($G$47="ERRO","ERRO",IF($G$47=0,0,G91/$G$47)) -> 0 | J91: =IF($I$47="ERRO","ERRO",IF($I$47=0,0,I91/$I$47)) -> 0
... B95: Outros Nao Operac. | D95: =IF($C$47="ERRO","ERRO",IF($C$47=0,0,C95/$C$47)) -> 0 | F95: =IF($E$47="ERRO","ERRO",IF($E$47=0,0,E95/$E$47)) -> 0 | H95: =IF($G$47="ERRO","ERRO",IF($G$47=0,0,G95/$G$47)) -> 0 | J95: =IF($I$47="ERRO","ERRO",IF($I$47=0,0,I95/$I$47)) -> 0
B97: RES. EXERC. FUT. | C97: 0 | D97: =IF($C$47="ERRO","ERRO",IF($C$47=0,0,C97/$C$47)) -> 0 | E97: 0 | F97: =IF($E$47="ERRO","ERRO",IF($E$47=0,0,E97/$E$47)) -> 0 | G97: 0 | H97: =IF($G$47="ERRO","ERRO",IF($G$47=0,0,G97/$G$47)) -> 0 | I97: 0 | J97: =IF($I$47="ERRO","ERRO",IF($I$47=0,0,I97/$I$47)) -> 0
B99: PARTIC. MINORIT. | C99: 0 | D99: =IF($C$47="ERRO","ERRO",IF($C$47=0,0,C99/$C$47)) -> 0 | E99: 0 | F99: =IF($E$47="ERRO","ERRO",IF($E$47=0,0,E99/$E$47)) -> 0 | G99: 0 | H99: =IF($G$47="ERRO","ERRO",IF($G$47=0,0,G99/$G$47)) -> 0 | I99: 0 | J99: =IF($I$47="ERRO","ERRO",IF($I$47=0,0,I99/$I$47)) -> 0
B101: PATRIMÔNIO LÍQUIDO | D101: =IF($C$47="ERRO","ERRO",IF($C$47=0,0,C101/$C$47)) -> 0 | F101: =IF($E$47="ERRO","ERRO",IF($E$47=0,0,E101/$E$47)) -> 0 | H101: =IF($G$47="ERRO","ERRO",IF($G$47=0,0,G101/$G$47)) -> 0 | J101: =IF($I$47="ERRO","ERRO",IF($I$47=0,0,I101/$I$47)) -> 0
B102: Capital e Reservas | C102: =C101-C103-C104 -> 0 | D102: =IF($C$47="ERRO","ERRO",IF($C$47=0,0,C102/$C$47)) -> 0 | E102: =E101-E103-E104 -> 0 | F102: =IF($E$47="ERRO","ERRO",IF($E$47=0,0,E102/$E$47)) -> 0 | G102: =G101-G103-G104 -> 0 | H102: =IF($G$47="ERRO","ERRO",IF($G$47=0,0,G102/$G$47)) -> 0 | I102: =I101-I103-I104 -> 0 | J102: =IF($I$47="ERRO","ERRO",IF($I$47=0,0,I102/$I$47)) -> 0
B103: Reservas de Reavaliação | D103: =IF($C$47="ERRO","ERRO",IF($C$47=0,0,C103/$C$47)) -> 0 | F103: =IF($E$47="ERRO","ERRO",IF($E$47=0,0,E103/$E$47)) -> 0 | H103: =IF($G$47="ERRO","ERRO",IF($G$47=0,0,G103/$G$47)) -> 0 | J103: =IF($I$47="ERRO","ERRO",IF($I$47=0,0,I103/$I$47)) -> 0
B104: Resultado do Período | C104: =C139 -> 0 | D104: =IF($C$47="ERRO","ERRO",IF($C$47=0,0,C104/$C$47)) -> 0 | E104: =E139 -> 0 | F104: =IF($E$47="ERRO","ERRO",IF($E$47=0,0,E104/$E$47)) -> 0 | G104: =G139 -> 0 | H104: =IF($G$47="ERRO","ERRO",IF($G$47=0,0,G104/$G$47)) -> 0 | I104: =I139 -> 0 | J104: =IF($I$47="ERRO","ERRO",IF($I$47=0,0,I104/$I$47)) -> 0
B106: DEMONSTRATIVO DE RESULTADOS
C107: JAN/2022-DEZ/2022 | E107: JAN/2023-DEZ/2023 | G107: JAN/2024-DEZ/2024 | I107: JAN/2025-DEZ/2025
B108: N° MESES DO PERIODO | C108: 12 | E108: 12 | G108: 12 | I108: 12
C109: R$MIL | D109: (%) | E109: R$MIL | F109: (%) | G109: R$MIL | H109: (%) | I109: R$MIL | J109: (%)
B111: FATUR. BRUTO | D111: =IF($C$113=0,0,C111/$C$113) -> 0 | F111: =IF($E$113=0,0,E111/$E$113) -> 0 | H111: =IF($G$113=0,0,G111/$G$113) -> 0 | J111: =IF($I$113=0,0,I111/$I$113) -> 0
B112: Impostos/Deduções | D112: =IF($C$113=0,0,C112/$C$113) -> 0 | F112: =IF($E$113=0,0,E112/$E$113) -> 0 | H112: =IF($G$113=0,0,G112/$G$113) -> 0 | J112: =IF($I$113=0,0,I112/$I$113) -> 0
B113: FATUR. LÍQUIDO | C113: =C111-C112 -> 0 | D113: =IF($C$113=0,0,C113/$C$113) -> 0 | E113: =E111-E112 -> 0 | F113: =IF($E$113=0,0,E113/$E$113) -> 0 | G113: =G111-G112 -> 0 | H113: =IF($G$113=0,0,G113/$G$113) -> 0 | I113: =I111-I112 -> 0 | J113: =IF($I$113=0,0,I113/$I$113) -> 0
B114: Custos | C114: =SUM(C115:C118) -> 0 | D114: =IF($C$113=0,0,C114/$C$113) -> 0 | E114: =SUM(E115:E118) -> 0 | F114: =IF($E$113=0,0,E114/$E$113) -> 0 | G114: =SUM(G115:G118) -> 0 | H114: =IF($G$113=0,0,G114/$G$113) -> 0 | I114: =SUM(I115:I118) -> 0 | J114: =IF($I$113=0,0,I114/$I$113) -> 0
B115: - Depreciação/Amortização | D115: =IF($C$113=0,0,C115/$C$113) -> 0 | F115: =IF($E$113=0,0,E115/$E$113) -> 0 | H115: =IF($G$113=0,0,G115/$G$113) -> 0 | J115: =IF($I$113=0,0,I115/$I$113) -> 0
B116: - Depreciação/Amortização Estimada | D116: =IF($C$113=0,0,C116/$C$113) -> 0 | F116: =IF($E$113=0,0,E116/$E$113) -> 0 | H116: =IF($G$113=0,0,G116/$G$113) -> 0 | J116: =IF($I$113=0,0,I116/$I$113) -> 0
B117: - Arrendamento Mercantil | D117: =IF($C$113=0,0,C117/$C$113) -> 0 | F117: =IF($E$113=0,0,E117/$E$113) -> 0 | H117: =IF($G$113=0,0,G117/$G$113) -> 0 | J117: =IF($I$113=0,0,I117/$I$113) -> 0
B118: - Custos Diretos | D118: =IF($C$113=0,0,C118/$C$113) -> 0 | F118: =IF($E$113=0,0,E118/$E$113) -> 0 | H118: =IF($G$113=0,0,G118/$G$113) -> 0 | J118: =IF($I$113=0,0,I118/$I$113) -> 0
B119: RES. BRUTO | C119: =C113-C114 -> 0 | D119: =IF($C$113=0,0,C119/$C$113) -> 0 | E119: =E113-E114 -> 0 | F119: =IF($E$113=0,0,E119/$E$113) -> 0 | G119: =G113-G114 -> 0 | H119: =IF($G$113=0,0,G119/$G$113) -> 0 | I119: =I113-I114 -> 0 | J119: =IF($I$113=0,0,I119/$I$113) -> 0
B120: Desps. Operac. | C120: =SUM(C121:C123) -> 0 | D120: =IF($C$113=0,0,C120/$C$113) -> 0 | E120: =SUM(E121:E123) -> 0 | F120: =IF($E$113=0,0,E120/$E$113) -> 0 | G120: =SUM(G121:G123) -> 0 | H120: =IF($G$113=0,0,G120/$G$113) -> 0 | I120: =SUM(I121:I123) -> 0 | J120: =IF($I$113=0,0,I120/$I$113) -> 0
B121: -Despesas Comerciais | D121: =IF($C$113=0,0,C121/$C$113) -> 0 | F121: =IF($E$113=0,0,E121/$E$113) -> 0 | H121: =IF($G$113=0,0,G121/$G$113) -> 0 | J121: =IF($I$113=0,0,I121/$I$113) -> 0
B122: -Despesas Administrativas | D122: =IF($C$113=0,0,C122/$C$113) -> 0 | F122: =IF($E$113=0,0,E122/$E$113) -> 0 | H122: =IF($G$113=0,0,G122/$G$113) -> 0 | J122: =IF($I$113=0,0,I122/$I$113) -> 0
B123: -Despesas c/ Depreciação | D123: =IF($C$113=0,0,C123/$C$113) -> 0 | F123: =IF($E$113=0,0,E123/$E$113) -> 0 | H123: =IF($G$113=0,0,G123/$G$113) -> 0 | J123: =IF($I$113=0,0,I123/$I$113) -> 0
B124: RES. ATIVIDADE | C124: =C119-C120 -> 0 | D124: =IF($C$113=0,0,C124/$C$113) -> 0 | E124: =E119-E120 -> 0 | F124: =IF($E$113=0,0,E124/$E$113) -> 0 | G124: =G119-G120 -> 0 | H124: =IF($G$113=0,0,G124/$G$113) -> 0 | I124: =I119-I120 -> 0 | J124: =IF($I$113=0,0,I124/$I$113) -> 0
B125: Despesas/(Receitas) Financ. Líq. | C125: =SUM(C126:C127) -> 0 | D125: =IF($C$113=0,0,C125/$C$113) -> 0 | E125: =SUM(E126:E127) -> 0 | F125: =IF($E$113=0,0,E125/$E$113) -> 0 | G125: =SUM(G126:G127) -> 0 | H125: =IF($G$113=0,0,G125/$G$113) -> 0 | I125: =SUM(I126:I127) -> 0 | J125: =IF($I$113=0,0,I125/$I$113) -> 0
B126: - Despesas Financeiras | D126: =IF($C$113=0,0,C126/$C$113) -> 0 | F126: =IF($E$113=0,0,E126/$E$113) -> 0 | H126: =IF($G$113=0,0,G126/$G$113) -> 0 | J126: =IF($I$113=0,0,I126/$I$113) -> 0
B127: - Receitas Financeiras | D127: =IF($C$113=0,0,C127/$C$113) -> 0 | F127: =IF($E$113=0,0,E127/$E$113) -> 0 | H127: =IF($G$113=0,0,G127/$G$113) -> 0 | J127: =IF($I$113=0,0,I127/$I$113) -> 0
B128: Variações Monetárias Líq. LP | D128: =IF($C$113=0,0,C128/$C$113) -> 0 | F128: =IF($E$113=0,0,E128/$E$113) -> 0 | H128: =IF($G$113=0,0,G128/$G$113) -> 0 | J128: =IF($I$113=0,0,I128/$I$113) -> 0
B129: Outras Rec./(Desp.) Operac. | D129: =IF($C$113=0,0,C129/$C$113) -> 0 | F129: =IF($E$113=0,0,E129/$E$113) -> 0 | H129: =IF($G$113=0,0,G129/$G$113) -> 0 | J129: =IF($I$113=0,0,I129/$I$113) -> 0
B130: RES. OPERACIONAL | C130: =C124-C125+C128+C129 -> 0 | D130: =IF($C$113=0,0,C130/$C$113) -> 0 | E130: =E124-E125+E128+E129 -> 0 | F130: =IF($E$113=0,0,E130/$E$113) -> 0 | G130: =G124-G125+G128+G129 -> 0 | H130: =IF($G$113=0,0,G130/$G$113) -> 0 | I130: =I124-I125+I128+I129 -> 0 | J130: =IF($I$113=0,0,I130/$I$113) -> 0
B131: Equivalência Patrimonial | D131: =IF($C$113=0,0,C131/$C$113) -> 0 | F131: =IF($E$113=0,0,E131/$E$113) -> 0 | H131: =IF($G$113=0,0,G131/$G$113) -> 0 | J131: =IF($I$113=0,0,I131/$I$113) -> 0
B132: Res. não Operacional | D132: =IF($C$113=0,0,C132/$C$113) -> 0 | F132: =IF($E$113=0,0,E132/$E$113) -> 0 | H132: =IF($G$113=0,0,G132/$G$113) -> 0 | J132: =IF($I$113=0,0,I132/$I$113) -> 0
B133: Correção Monetária | D133: =IF($C$113=0,0,C133/$C$113) -> 0 | F133: =IF($E$113=0,0,E133/$E$113) -> 0 | H133: =IF($G$113=0,0,G133/$G$113) -> 0 | J133: =IF($I$113=0,0,I133/$I$113) -> 0
...

Sheet EMP_2
B1: TOTAL ATIVO | C1: =SUM(C11+C29+C42) -> 0 | E1: =SUM(E11+E29+E42) -> 0 | G1: =SUM(G11+G29+G42) -> 0 | I1: =SUM(I11+I29+I42) -> 0
B2: TOTAL PASSIVO | C2: =C51+C79+C97+C99+C101 -> 0 | E2: =E51+E79+E97+E99+E101 -> 0 | G2: =G51+G79+G97+G99+G101 -> 0 | I2: =I51+I79+I97+I99+I101 -> 0
B3: DIFERENÇA | C3: =C1-C2 -> 0 | E3: =E1-E2 -> 0 | G3: =G1-G2 -> 0 | I3: =I1-I2 -> 0
B5: EMPRESA 2 LTDA
B7: BALANÇO PATRIMONIAL
C8: 44896 | E8: 45261 | G8: 45627 | I8: 45992
B9: ATIVO | C9: R$ MIL | D9: (%) | E9: R$ MIL | F9: (%) | G9: R$ MIL | H9: (%) | I9: R$ MIL | J9: (%)
B11: CIRCULANTE | C11: =SUM(C12:C27) -> 0 | D11: =IF($C$48="ERRO","ERRO",IF($C$48=0,0,C11/$C$48)) -> 0 | E11: =SUM(E12:E27) -> 0 | F11: =IF($E$48="ERRO","ERRO",IF($E$48=0,0,E11/$E$48)) -> 0 | G11: =SUM(G12:G27) -> 0 | H11: =IF($G$48="ERRO","ERRO",IF($G$48=0,0,G11/$G$48)) -> 0 | I11: =SUM(I12:I27) -> 0 | J11: =IF($I$48="ERRO","ERRO",IF($I$48=0,0,I11/$I$48)) -> 0
B12: Caixa e Bancos | D12: =IF($C$48="ERRO","ERRO",IF($C$48=0,0,C12/$C$48)) -> 0 | F12: =IF($E$48="ERRO","ERRO",IF($E$48=0,0,E12/$E$48)) -> 0 | H12: =IF($G$48="ERRO","ERRO",IF($G$48=0,0,G12/$G$48)) -> 0 | J12: =IF($I$48="ERRO","ERRO",IF($I$48=0,0,I12/$I$48)) -> 0
B13: Aplicações Financeiras | D13: =IF($C$48="ERRO","ERRO",IF($C$48=0,0,C13/$C$48)) -> 0 | F13: =IF($E$48="ERRO","ERRO",IF($E$48=0,0,E13/$E$48)) -> 0 | H13: =IF($G$48="ERRO","ERRO",IF($G$48=0,0,G13/$G$48)) -> 0 | J13: =IF($I$48="ERRO","ERRO",IF($I$48=0,0,I13/$I$48)) -> 0
B14: Contas a Receber | D14: =IF($C$48="ERRO","ERRO",IF($C$48=0,0,C14/$C$48)) -> 0 | F14: =IF($E$48="ERRO","ERRO",IF($E$48=0,0,E14/$E$48)) -> 0 | H14: =IF($G$48="ERRO","ERRO",IF($G$48=0,0,G14/$G$48)) -> 0 | J14: =IF($I$48="ERRO","ERRO",IF($I$48=0,0,I14/$I$48)) -> 0
B15: Cooperados | D15: =IF($C$48="ERRO","ERRO",IF($C$48=0,0,C15/$C$48)) -> 0 | F15: =IF($E$48="ERRO","ERRO",IF($E$48=0,0,E15/$E$48)) -> 0 | H15: =IF($G$48="ERRO","ERRO",IF($G$48=0,0,G15/$G$48)) -> 0 | J15: =IF($I$48="ERRO","ERRO",IF($I$48=0,0,I15/$I$48)) -> 0
B16: CVA | D16: =IF($C$48="ERRO","ERRO",IF($C$48=0,0,C16/$C$48)) -> 0 | F16: =IF($E$48="ERRO","ERRO",IF($E$48=0,0,E16/$E$48)) -> 0 | H16: =IF($G$48="ERRO","ERRO",IF($G$48=0,0,G16/$G$48)) -> 0 | J16: =IF($I$48="ERRO","ERRO",IF($I$48=0,0,I16/$I$48)) -> 0
B17: Estoques | D17: =IF($C$48="ERRO","ERRO",IF($C$48=0,0,C17/$C$48)) -> 0 | F17: =IF($E$48="ERRO","ERRO",IF($E$48=0,0,E17/$E$48)) -> 0 | H17: =IF($G$48="ERRO","ERRO",IF($G$48=0,0,G17/$G$48)) -> 0 | J17: =IF($I$48="ERRO","ERRO",IF($I$48=0,0,I17/$I$48)) -> 0
B18: Adiant. a Fornecedores | D18: =IF($C$48="ERRO","ERRO",IF($C$48=0,0,C18/$C$48)) -> 0 | F18: =IF($E$48="ERRO","ERRO",IF($E$48=0,0,E18/$E$48)) -> 0 | H18: =IF($G$48="ERRO","ERRO",IF($G$48=0,0,G18/$G$48)) -> 0 | J18: =IF($I$48="ERRO","ERRO",IF($I$48=0,0,I18/$I$48)) -> 0
B19: Créditos a Fumicultores | D19: =IF($C$48="ERRO","ERRO",IF($C$48=0,0,C19/$C$48)) -> 0 | F19: =IF($E$48="ERRO","ERRO",IF($E$48=0,0,E19/$E$48)) -> 0 | H19: =IF($G$48="ERRO","ERRO",IF($G$48=0,0,G19/$G$48)) -> 0 | J19: =IF($I$48="ERRO","ERRO",IF($I$48=0,0,I19/$I$48)) -> 0
B20: Despesas Antecipadas | D20: =IF($C$48="ERRO","ERRO",IF($C$48=0,0,C20/$C$48)) -> 0 | F20: =IF($E$48="ERRO","ERRO",IF($E$48=0,0,E20/$E$48)) -> 0 | H20: =IF($G$48="ERRO","ERRO",IF($G$48=0,0,G20/$G$48)) -> 0 | J20: =IF($I$48="ERRO","ERRO",IF($I$48=0,0,I20/$I$48)) -> 0
B21: Impostos a Recuperar | D21: =IF($C$48="ERRO","ERRO",IF($C$48=0,0,C21/$C$48)) -> 0 | F21: =IF($E$48="ERRO","ERRO",IF($E$48=0,0,E21/$E$48)) -> 0 | H21: =IF($G$48="ERRO","ERRO",IF($G$48=0,0,G21/$G$48)) -> 0 | J21: =IF($I$48="ERRO","ERRO",IF($I$48=0,0,I21/$I$48)) -> 0
B22: Dividendos a Receber | D22: =IF($C$48="ERRO","ERRO",IF($C$48=0,0,C22/$C$48)) -> 0 | F22: =IF($E$48="ERRO","ERRO",IF($E$48=0,0,E22/$E$48)) -> 0 | H22: =IF($G$48="ERRO","ERRO",IF($G$48=0,0,G22/$G$48)) -> 0 | J22: =IF($I$48="ERRO","ERRO",IF($I$48=0,0,I22/$I$48)) -> 0
B23: Imposto Diferido | D23: =IF($C$48="ERRO","ERRO",IF($C$48=0,0,C23/$C$48)) -> 0 | F23: =IF($E$48="ERRO","ERRO",IF($E$48=0,0,E23/$E$48)) -> 0 | H23: =IF($G$48="ERRO","ERRO",IF($G$48=0,0,G23/$G$48)) -> 0 | J23: =IF($I$48="ERRO","ERRO",IF($I$48=0,0,I23/$I$48)) -> 0
... B27: Outros Nao Operac. | D27: =IF($C$48="ERRO","ERRO",IF($C$48=0,0,C27/$C$48)) -> 0 | F27: =IF($E$48="ERRO","ERRO",IF($E$48=0,0,E27/$E$48)) -> 0 | H27: =IF($G$48="ERRO","ERRO",IF($G$48=0,0,G27/$G$48)) -> 0 | J27: =IF($I$48="ERRO","ERRO",IF($I$48=0,0,I27/$I$48)) -> 0
B29: REALIZ. L.P. | C29: =SUM(C30:C40) -> 0 | D29: =IF($C$48="ERRO","ERRO",IF($C$48=0,0,C29/$C$48)) -> 0 | E29: =SUM(E30:E40) -> 0 | F29: =IF($E$48="ERRO","ERRO",IF($E$48=0,0,E29/$E$48)) -> 0 | G29: =SUM(G30:G40) -> 0 | H29: =IF($G$48="ERRO","ERRO",IF($G$48=0,0,G29/$G$48)) -> 0 | I29: =SUM(I30:I40) -> 0 | J29: =IF($I$48="ERRO","ERRO",IF($I$48=0,0,I29/$I$48)) -> 0
B30: Contas a Receber | D30: =IF($C$48="ERRO","ERRO",IF($C$48=0,0,C30/$C$48)) -> 0 | F30: =IF($E$48="ERRO","ERRO",IF($E$48=0,0,E30/$E$48)) -> 0 | H30: =IF($G$48="ERRO","ERRO",IF($G$48=0,0,G30/$G$48)) -> 0 | J30: =IF($I$48="ERRO","ERRO",IF($I$48=0,0,I30/$I$48)) -> 0
B31: Cooperados | D31: =IF($C$48="ERRO","ERRO",IF($C$48=0,0,C31/$C$48)) -> 0 | F31: =IF($E$48="ERRO","ERRO",IF($E$48=0,0,E31/$E$48)) -> 0 | H31: =IF($G$48="ERRO","ERRO",IF($G$48=0,0,G31/$G$48)) -> 0 | J31: =IF($I$48="ERRO","ERRO",IF($I$48=0,0,I31/$I$48)) -> 0
B32: C/C Coligadas/Acionistas | D32: =IF($C$48="ERRO","ERRO",IF($C$48=0,0,C32/$C$48)) -> 0 | F32: =IF($E$48="ERRO","ERRO",IF($E$48=0,0,E32/$E$48)) -> 0 | H32: =IF($G$48="ERRO","ERRO",IF($G$48=0,0,G32/$G$48)) -> 0 | J32: =IF($I$48="ERRO","ERRO",IF($I$48=0,0,I32/$I$48)) -> 0
B33: Depósitos Judiciais | D33: =IF($C$48="ERRO","ERRO",IF($C$48=0,0,C33/$C$48)) -> 0 | F33: =IF($E$48="ERRO","ERRO",IF($E$48=0,0,E33/$E$48)) -> 0 | H33: =IF($G$48="ERRO","ERRO",IF($G$48=0,0,G33/$G$48)) -> 0 | J33: =IF($I$48="ERRO","ERRO",IF($I$48=0,0,I33/$I$48)) -> 0
B34: Imposto Diferido | D34: =IF($C$48="ERRO","ERRO",IF($C$48=0,0,C34/$C$48)) -> 0 | F34: =IF($E$48="ERRO","ERRO",IF($E$48=0,0,E34/$E$48)) -> 0 | H34: =IF($G$48="ERRO","ERRO",IF($G$48=0,0,G34/$G$48)) -> 0 | J34: =IF($I$48="ERRO","ERRO",IF($I$48=0,0,I34/$I$48)) -> 0
B35: Créditos a Fumicultores | D35: =IF($C$48="ERRO","ERRO",IF($C$48=0,0,C35/$C$48)) -> 0 | F35: =IF($E$48="ERRO","ERRO",IF($E$48=0,0,E35/$E$48)) -> 0 | H35: =IF($G$48="ERRO","ERRO",IF($G$48=0,0,G35/$G$48)) -> 0 | J35: =IF($I$48="ERRO","ERRO",IF($I$48=0,0,I35/$I$48)) -> 0
B36: CTN´s | D36: =IF($C$48="ERRO","ERRO",IF($C$48=0,0,C36/$C$48)) -> 0 | F36: =IF($E$48="ERRO","ERRO",IF($E$48=0,0,E36/$E$48)) -> 0 | H36: =IF($G$48="ERRO","ERRO",IF($G$48=0,0,G36/$G$48)) -> 0 | J36: =IF($I$48="ERRO","ERRO",IF($I$48=0,0,I36/$I$48)) -> 0
B37: Outros Operac. | D37: =IF($C$48="ERRO","ERRO",IF($C$48=0,0,C37/$C$48)) -> 0 | F37: =IF($E$48="ERRO","ERRO",IF($E$48=0,0,E37/$E$48)) -> 0 | H37: =IF($G$48="ERRO","ERRO",IF($G$48=0,0,G37/$G$48)) -> 0 | J37: =IF($I$48="ERRO","ERRO",IF($I$48=0,0,I37/$I$48)) -> 0
B38: Outros Operac. | D38: =IF($C$48="ERRO","ERRO",IF($C$48=0,0,C38/$C$48)) -> 0 | F38: =IF($E$48="ERRO","ERRO",IF($E$48=0,0,E38/$E$48)) -> 0 | H38: =IF($G$48="ERRO","ERRO",IF($G$48=0,0,G38/$G$48)) -> 0 | J38: =IF($I$48="ERRO","ERRO",IF($I$48=0,0,I38/$I$48)) -> 0
B39: Outros Nao Operac. | D39: =IF($C$48="ERRO","ERRO",IF($C$48=0,0,C39/$C$48)) -> 0 | F39: =IF($E$48="ERRO","ERRO",IF($E$48=0,0,E39/$E$48)) -> 0 | H39: =IF($G$48="ERRO","ERRO",IF($G$48=0,0,G39/$G$48)) -> 0 | J39: =IF($I$48="ERRO","ERRO",IF($I$48=0,0,I39/$I$48)) -> 0
B40: Outros Nao Operac. | D40: =IF($C$48="ERRO","ERRO",IF($C$48=0,0,C40/$C$48)) -> 0 | F40: =IF($E$48="ERRO","ERRO",IF($E$48=0,0,E40/$E$48)) -> 0 | H40: =IF($G$48="ERRO","ERRO",IF($G$48=0,0,G40/$G$48)) -> 0 | J40: =IF($I$48="ERRO","ERRO",IF($I$48=0,0,I40/$I$48)) -> 0
B42: PERMANENTE | C42: =SUM(C43:C45) -> 0 | D42: =IF($C$48="ERRO","ERRO",IF($C$48=0,0,C42/$C$48)) -> 0 | E42: =SUM(E43:E45) -> 0 | F42: =IF($E$48="ERRO","ERRO",IF($E$48=0,0,E42/$E$48)) -> 0 | G42: =SUM(G43:G45) -> 0 | H42: =IF($G$48="ERRO","ERRO",IF($G$48=0,0,G42/$G$48)) -> 0 | I42: =SUM(I43:I45) -> 0 | J42: =IF($I$48="ERRO","ERRO",IF($I$48=0,0,I42/$I$48)) -> 0
B43: Imobilizado Técnico | D43: =IF($C$48="ERRO","ERRO",IF($C$48=0,0,C43/$C$48)) -> 0 | F43: =IF($E$48="ERRO","ERRO",IF($E$48=0,0,E43/$E$48)) -> 0 | H43: =IF($G$48="ERRO","ERRO",IF($G$48=0,0,G43/$G$48)) -> 0 | J43: =IF($I$48="ERRO","ERRO",IF($I$48=0,0,I43/$I$48)) -> 0
B44: Investimentos | D44: =IF($C$48="ERRO","ERRO",IF($C$48=0,0,C44/$C$48)) -> 0 | F44: =IF($E$48="ERRO","ERRO",IF($E$48=0,0,E44/$E$48)) -> 0 | H44: =IF($G$48="ERRO","ERRO",IF($G$48=0,0,G44/$G$48)) -> 0 | J44: =IF($I$48="ERRO","ERRO",IF($I$48=0,0,I44/$I$48)) -> 0
B45: Diferido/Intangível | D45: =IF($C$48="ERRO","ERRO",IF($C$48=0,0,C45/$C$48)) -> 0 | F45: =IF($E$48="ERRO","ERRO",IF($E$48=0,0,E45/$E$48)) -> 0 | H45: =IF($G$48="ERRO","ERRO",IF($G$48=0,0,G45/$G$48)) -> 0 | J45: =IF($I$48="ERRO","ERRO",IF($I$48=0,0,I45/$I$48)) -> 0
B47: TOTAL | C47: =IF(OR(C11+C29+C42-C51-C79-C97-C99-C101>1,C11+C29+C42-C51-C79-C97-C99-C101<-1),"ERRO",C11+C29+C42) -> 0 | D47: =IF($C$48="ERRO","ERRO",IF($C$48=0,0,C47/$C$48)) -> 0 | E47: =IF(OR(E11+E29+E42-E51-E79-E97-E99-E101>1,E11+E29+E42-E51-E79-E97-E99-E101<-1),"ERRO",E11+E29+E42) -> 0 | F47: =IF($E$48="ERRO","ERRO",IF($E$48=0,0,E47/$E$48)) -> 0 | G47: =IF(OR(G11+G29+G42-G51-G79-G97-G99-G101>1,G11+G29+G42-G51-G79-G97-G99-G101<-1),"ERRO",G11+G29+G42) -> 0 | H47: =IF($G$48="ERRO","ERRO",IF($G$48=0,0,G47/$G$48)) -> 0 | I47: =IF(OR(I11+I29+I42-I51-I79-I97-I99-I101>1,I11+I29+I42-I51-I79-I97-I99-I101<-1),"ERRO",I11+I29+I42) -> 0 | J47: =IF($I$48="ERRO","ERRO",IF($I$48=0,0,I47/$I$48)) -> 0
B49: PASSIVO | C49: R$ MIL | D49: (%) | E49: R$ MIL | F49: (%) | G49: R$ MIL | H49: (%) | I49: R$ MIL | J49: (%)
B51: CIRCULANTE | C51: =SUM(C52:C77) -> 0 | D51: =IF($C$48="ERRO","ERRO",IF($C$48=0,0,C51/$C$48)) -> 0 | E51: =SUM(E52:E77) -> 0 | F51: =IF($E$48="ERRO","ERRO",IF($E$48=0,0,E51/$E$48)) -> 0 | G51: =SUM(G52:G77) -> 0 | H51: =IF($G$48="ERRO","ERRO",IF($G$48=0,0,G51/$G$48)) -> 0 | I51: =SUM(I52:I77) -> 0 | J51: =IF($I$48="ERRO","ERRO",IF($I$48=0,0,I51/$I$48)) -> 0
B52: Fornecedores Nacionais | D52: =IF($C$48="ERRO","ERRO",IF($C$48=0,0,C52/$C$48)) -> 0 | F52: =IF($E$48="ERRO","ERRO",IF($E$48=0,0,E52/$E$48)) -> 0 | H52: =IF($G$48="ERRO","ERRO",IF($G$48=0,0,G52/$G$48)) -> 0 | J52: =IF($I$48="ERRO","ERRO",IF($I$48=0,0,I52/$I$48)) -> 0
B53: Fornecedores Estrangeiros | D53: =IF($C$48="ERRO","ERRO",IF($C$48=0,0,C53/$C$48)) -> 0 | F53: =IF($E$48="ERRO","ERRO",IF($E$48=0,0,E53/$E$48)) -> 0 | H53: =IF($G$48="ERRO","ERRO",IF($G$48=0,0,G53/$G$48)) -> 0 | J53: =IF($I$48="ERRO","ERRO",IF($I$48=0,0,I53/$I$48)) -> 0
B54: Empréstimos Bancários | D54: =IF($C$48="ERRO","ERRO",IF($C$48=0,0,C54/$C$48)) -> 0 | F54: =IF($E$48="ERRO","ERRO",IF($E$48=0,0,E54/$E$48)) -> 0 | H54: =IF($G$48="ERRO","ERRO",IF($G$48=0,0,G54/$G$48)) -> 0 | J54: =IF($I$48="ERRO","ERRO",IF($I$48=0,0,I54/$I$48)) -> 0
B55: Financiamentos Operacionais | D55: =IF($C$48="ERRO","ERRO",IF($C$48=0,0,C55/$C$48)) -> 0 | F55: =IF($E$48="ERRO","ERRO",IF($E$48=0,0,E55/$E$48)) -> 0 | H55: =IF($G$48="ERRO","ERRO",IF($G$48=0,0,G55/$G$48)) -> 0 | J55: =IF($I$48="ERRO","ERRO",IF($I$48=0,0,I55/$I$48)) -> 0
B56: Financiamentos c/ Tradings | D56: =IF($C$48="ERRO","ERRO",IF($C$48=0,0,C56/$C$48)) -> 0 | F56: =IF($E$48="ERRO","ERRO",IF($E$48=0,0,E56/$E$48)) -> 0 | H56: =IF($G$48="ERRO","ERRO",IF($G$48=0,0,G56/$G$48)) -> 0 | J56: =IF($I$48="ERRO","ERRO",IF($I$48=0,0,I56/$I$48)) -> 0
B57: Parcelas Correntes Financ. L.P. | D57: =IF($C$48="ERRO","ERRO",IF($C$48=0,0,C57/$C$48)) -> 0 | F57: =IF($E$48="ERRO","ERRO",IF($E$48=0,0,E57/$E$48)) -> 0 | H57: =IF($G$48="ERRO","ERRO",IF($G$48=0,0,G57/$G$48)) -> 0 | J57: =IF($I$48="ERRO","ERRO",IF($I$48=0,0,I57/$I$48)) -> 0
B58: Debêntures | D58: =IF($C$48="ERRO","ERRO",IF($C$48=0,0,C58/$C$48)) -> 0 | F58: =IF($E$48="ERRO","ERRO",IF($E$48=0,0,E58/$E$48)) -> 0 | H58: =IF($G$48="ERRO","ERRO",IF($G$48=0,0,G58/$G$48)) -> 0 | J58: =IF($I$48="ERRO","ERRO",IF($I$48=0,0,I58/$I$48)) -> 0
B59: Swap | D59: =IF($C$48="ERRO","ERRO",IF($C$48=0,0,C59/$C$48)) -> 0 | F59: =IF($E$48="ERRO","ERRO",IF($E$48=0,0,E59/$E$48)) -> 0 | H59: =IF($G$48="ERRO","ERRO",IF($G$48=0,0,G59/$G$48)) -> 0 | J59: =IF($I$48="ERRO","ERRO",IF($I$48=0,0,I59/$I$48)) -> 0
B60: Securitização | D60: =IF($C$48="ERRO","ERRO",IF($C$48=0,0,C60/$C$48)) -> 0 | F60: =IF($E$48="ERRO","ERRO",IF($E$48=0,0,E60/$E$48)) -> 0 | H60: =IF($G$48="ERRO","ERRO",IF($G$48=0,0,G60/$G$48)) -> 0 | J60: =IF($I$48="ERRO","ERRO",IF($I$48=0,0,I60/$I$48)) -> 0
B61: Leasing | D61: =IF($C$48="ERRO","ERRO",IF($C$48=0,0,C61/$C$48)) -> 0 | F61: =IF($E$48="ERRO","ERRO",IF($E$48=0,0,E61/$E$48)) -> 0 | H61: =IF($G$48="ERRO","ERRO",IF($G$48=0,0,G61/$G$48)) -> 0 | J61: =IF($I$48="ERRO","ERRO",IF($I$48=0,0,I61/$I$48)) -> 0
B62: Salários e Encargos | D62: =IF($C$48="ERRO","ERRO",IF($C$48=0,0,C62/$C$48)) -> 0 | F62: =IF($E$48="ERRO","ERRO",IF($E$48=0,0,E62/$E$48)) -> 0 | H62: =IF($G$48="ERRO","ERRO",IF($G$48=0,0,G62/$G$48)) -> 0 | J62: =IF($I$48="ERRO","ERRO",IF($I$48=0,0,I62/$I$48)) -> 0
B63: Tributos e Obrigações Fiscais | D63: =IF($C$48="ERRO","ERRO",IF($C$48=0,0,C63/$C$48)) -> 0 | F63: =IF($E$48="ERRO","ERRO",IF($E$48=0,0,E63/$E$48)) -> 0 | H63: =IF($G$48="ERRO","ERRO",IF($G$48=0,0,G63/$G$48)) -> 0 | J63: =IF($I$48="ERRO","ERRO",IF($I$48=0,0,I63/$I$48)) -> 0
... B77: Outros Nao Operac. | D77: =IF($C$48="ERRO","ERRO",IF($C$48=0,0,C77/$C$48)) -> 0 | F77: =IF($E$48="ERRO","ERRO",IF($E$48=0,0,E77/$E$48)) -> 0 | H77: =IF($G$48="ERRO","ERRO",IF($G$48=0,0,G77/$G$48)) -> 0 | J77: =IF($I$48="ERRO","ERRO",IF($I$48=0,0,I77/$I$48)) -> 0
B79: EXIGÍVEL L.P. | C79: =SUM(C80:C95) -> 0 | D79: =IF($C$48="ERRO","ERRO",IF($C$48=0,0,C79/$C$48)) -> 0 | E79: =SUM(E80:E95) -> 0 | F79: =IF($E$48="ERRO","ERRO",IF($E$48=0,0,E79/$E$48)) -> 0 | G79: =SUM(G80:G95) -> 0 | H79: =IF($G$48="ERRO","ERRO",IF($G$48=0,0,G79/$G$48)) -> 0 | I79: =SUM(I80:I95) -> 0 | J79: =IF($I$48="ERRO","ERRO",IF($I$48=0,0,I79/$I$48)) -> 0
B80: Empréstimos e Financiamentos | D80: =IF($C$48="ERRO","ERRO",IF($C$48=0,0,C80/$C$48)) -> 0 | F80: =IF($E$48="ERRO","ERRO",IF($E$48=0,0,E80/$E$48)) -> 0 | H80: =IF($G$48="ERRO","ERRO",IF($G$48=0,0,G80/$G$48)) -> 0 | J80: =IF($I$48="ERRO","ERRO",IF($I$48=0,0,I80/$I$48)) -> 0
B81: Debêntures | D81: =IF($C$48="ERRO","ERRO",IF($C$48=0,0,C81/$C$48)) -> 0 | F81: =IF($E$48="ERRO","ERRO",IF($E$48=0,0,E81/$E$48)) -> 0 | H81: =IF($G$48="ERRO","ERRO",IF($G$48=0,0,G81/$G$48)) -> 0 | J81: =IF($I$48="ERRO","ERRO",IF($I$48=0,0,I81/$I$48)) -> 0
B82: Leasing | D82: =IF($C$48="ERRO","ERRO",IF($C$48=0,0,C82/$C$48)) -> 0 | F82: =IF($E$48="ERRO","ERRO",IF($E$48=0,0,E82/$E$48)) -> 0 | H82: =IF($G$48="ERRO","ERRO",IF($G$48=0,0,G82/$G$48)) -> 0 | J82: =IF($I$48="ERRO","ERRO",IF($I$48=0,0,I82/$I$48)) -> 0
B83: Financiamentos c/ Tradings | D83: =IF($C$48="ERRO","ERRO",IF($C$48=0,0,C83/$C$48)) -> 0 | F83: =IF($E$48="ERRO","ERRO",IF($E$48=0,0,E83/$E$48)) -> 0 | H83: =IF($G$48="ERRO","ERRO",IF($G$48=0,0,G83/$G$48)) -> 0 | J83: =IF($I$48="ERRO","ERRO",IF($I$48=0,0,I83/$I$48)) -> 0
B84: Securitização | D84: =IF($C$48="ERRO","ERRO",IF($C$48=0,0,C84/$C$48)) -> 0 | F84: =IF($E$48="ERRO","ERRO",IF($E$48=0,0,E84/$E$48)) -> 0 | H84: =IF($G$48="ERRO","ERRO",IF($G$48=0,0,G84/$G$48)) -> 0 | J84: =IF($I$48="ERRO","ERRO",IF($I$48=0,0,I84/$I$48)) -> 0
B85: Custo Orçado | D85: =IF($C$48="ERRO","ERRO",IF($C$48=0,0,C85/$C$48)) -> 0 | F85: =IF($E$48="ERRO","ERRO",IF($E$48=0,0,E85/$E$48)) -> 0 | H85: =IF($G$48="ERRO","ERRO",IF($G$48=0,0,G85/$G$48)) -> 0 | J85: =IF($I$48="ERRO","ERRO",IF($I$48=0,0,I85/$I$48)) -> 0
B86: Terrenos | D86: =IF($C$48="ERRO","ERRO",IF($C$48=0,0,C86/$C$48)) -> 0 | F86: =IF($E$48="ERRO","ERRO",IF($E$48=0,0,E86/$E$48)) -> 0 | H86: =IF($G$48="ERRO","ERRO",IF($G$48=0,0,G86/$G$48)) -> 0 | J86: =IF($I$48="ERRO","ERRO",IF($I$48=0,0,I86/$I$48)) -> 0
B87: Outorga | D87: =IF($C$48="ERRO","ERRO",IF($C$48=0,0,C87/$C$48)) -> 0 | F87: =IF($E$48="ERRO","ERRO",IF($E$48=0,0,E87/$E$48)) -> 0 | H87: =IF($G$48="ERRO","ERRO",IF($G$48=0,0,G87/$G$48)) -> 0 | J87: =IF($I$48="ERRO","ERRO",IF($I$48=0,0,I87/$I$48)) -> 0
B88: Compromissos Consorciados | D88: =IF($C$48="ERRO","ERRO",IF($C$48=0,0,C88/$C$48)) -> 0 | F88: =IF($E$48="ERRO","ERRO",IF($E$48=0,0,E88/$E$48)) -> 0 | H88: =IF($G$48="ERRO","ERRO",IF($G$48=0,0,G88/$G$48)) -> 0 | J88: =IF($I$48="ERRO","ERRO",IF($I$48=0,0,I88/$I$48)) -> 0
B89: Plano de Previdênciário | D89: =IF($C$48="ERRO","ERRO",IF($C$48=0,0,C89/$C$48)) -> 0 | F89: =IF($E$48="ERRO","ERRO",IF($E$48=0,0,E89/$E$48)) -> 0 | H89: =IF($G$48="ERRO","ERRO",IF($G$48=0,0,G89/$G$48)) -> 0 | J89: =IF($I$48="ERRO","ERRO",IF($I$48=0,0,I89/$I$48)) -> 0
B90: Dividendos a pagar | D90: =IF($C$48="ERRO","ERRO",IF($C$48=0,0,C90/$C$48)) -> 0 | F90: =IF($E$48="ERRO","ERRO",IF($E$48=0,0,E90/$E$48)) -> 0 | H90: =IF($G$48="ERRO","ERRO",IF($G$48=0,0,G90/$G$48)) -> 0 | J90: =IF($I$48="ERRO","ERRO",IF($I$48=0,0,I90/$I$48)) -> 0
B91: Provisão para Contingência | D91: =IF($C$48="ERRO","ERRO",IF($C$48=0,0,C91/$C$48)) -> 0 | F91: =IF($E$48="ERRO","ERRO",IF($E$48=0,0,E91/$E$48)) -> 0 | H91: =IF($G$48="ERRO","ERRO",IF($G$48=0,0,G91/$G$48)) -> 0 | J91: =IF($I$48="ERRO","ERRO",IF($I$48=0,0,I91/$I$48)) -> 0
... B95: Outros Nao Operac. | D95: =IF($C$48="ERRO","ERRO",IF($C$48=0,0,C95/$C$48)) -> 0 | F95: =IF($E$48="ERRO","ERRO",IF($E$48=0,0,E95/$E$48)) -> 0 | H95: =IF($G$48="ERRO","ERRO",IF($G$48=0,0,G95/$G$48)) -> 0 | J95: =IF($I$48="ERRO","ERRO",IF($I$48=0,0,I95/$I$48)) -> 0
B97: RES. EXERC. FUT. | C97: 0 | D97: =IF($C$48="ERRO","ERRO",IF($C$48=0,0,C97/$C$48)) -> 0 | E97: 0 | F97: =IF($E$48="ERRO","ERRO",IF($E$48=0,0,E97/$E$48)) -> 0 | G97: 0 | H97: =IF($G$48="ERRO","ERRO",IF($G$48=0,0,G97/$G$48)) -> 0 | I97: 0 | J97: =IF($I$48="ERRO","ERRO",IF($I$48=0,0,I97/$I$48)) -> 0
B99: PARTIC. MINORIT. | C99: 0 | D99: =IF($C$48="ERRO","ERRO",IF($C$48=0,0,C99/$C$48)) -> 0 | E99: 0 | F99: =IF($E$48="ERRO","ERRO",IF($E$48=0,0,E99/$E$48)) -> 0 | G99: 0 | H99: =IF($G$48="ERRO","ERRO",IF($G$48=0,0,G99/$G$48)) -> 0 | I99: 0 | J99: =IF($I$48="ERRO","ERRO",IF($I$48=0,0,I99/$I$48)) -> 0
B101: PATRIMÔNIO LÍQUIDO | D101: =IF($C$48="ERRO","ERRO",IF($C$48=0,0,C101/$C$48)) -> 0 | F101: =IF($E$48="ERRO","ERRO",IF($E$48=0,0,E101/$E$48)) -> 0 | H101: =IF($G$48="ERRO","ERRO",IF($G$48=0,0,G101/$G$48)) -> 0 | J101: =IF($I$48="ERRO","ERRO",IF($I$48=0,0,I101/$I$48)) -> 0
B102: Capital e Reservas | C102: =C101-C103-C104 -> 0 | D102: =IF($C$48="ERRO","ERRO",IF($C$48=0,0,C102/$C$48)) -> 0 | E102: =E101-E103-E104 -> 0 | F102: =IF($E$48="ERRO","ERRO",IF($E$48=0,0,E102/$E$48)) -> 0 | G102: =G101-G103-G104 -> 0 | H102: =IF($G$48="ERRO","ERRO",IF($G$48=0,0,G102/$G$48)) -> 0 | I102: =I101-I103-I104 -> 0 | J102: =IF($I$48="ERRO","ERRO",IF($I$48=0,0,I102/$I$48)) -> 0
B103: Reservas de Reavaliação | D103: =IF($C$48="ERRO","ERRO",IF($C$48=0,0,C103/$C$48)) -> 0 | F103: =IF($E$48="ERRO","ERRO",IF($E$48=0,0,E103/$E$48)) -> 0 | H103: =IF($G$48="ERRO","ERRO",IF($G$48=0,0,G103/$G$48)) -> 0 | J103: =IF($I$48="ERRO","ERRO",IF($I$48=0,0,I103/$I$48)) -> 0
B104: Resultado do Período | C104: =C139 -> 0 | D104: =IF($C$48="ERRO","ERRO",IF($C$48=0,0,C104/$C$48)) -> 0 | E104: =E139 -> 0 | F104: =IF($E$48="ERRO","ERRO",IF($E$48=0,0,E104/$E$48)) -> 0 | G104: =G139 -> 0 | H104: =IF($G$48="ERRO","ERRO",IF($G$48=0,0,G104/$G$48)) -> 0 | I104: =I139 -> 0 | J104: =IF($I$48="ERRO","ERRO",IF($I$48=0,0,I104/$I$48)) -> 0
B106: DEMONSTRATIVO DE RESULTADOS
C107: JAN/2022-DEZ/2022 | E107: JAN/2023-DEZ/2023 | G107: JAN/2024-DEZ/2024 | I107: JAN/2025-DEZ/2025
B108: N° MESES DO PERIODO | C108: 12 | E108: 12 | G108: 12 | I108: 12
C109: R$MIL | D109: (%) | E109: R$MIL | F109: (%) | G109: R$MIL | H109: (%) | I109: R$MIL | J109: (%)
B111: FATUR. BRUTO | D111: =IF($C$114=0,0,C111/$C$114) -> 0 | F111: =IF($E$114=0,0,E111/$E$114) -> 0 | H111: =IF($G$114=0,0,G111/$G$114) -> 0 | J111: =IF($I$114=0,0,I111/$I$114) -> 0
B112: Impostos/Deduções | D112: =IF($C$114=0,0,C112/$C$114) -> 0 | F112: =IF($E$114=0,0,E112/$E$114) -> 0 | H112: =IF($G$114=0,0,G112/$G$114) -> 0 | J112: =IF($I$114=0,0,I112/$I$114) -> 0
B113: FATUR. LÍQUIDO | C113: =C111-C112 -> 0 | D113: =IF($C$114=0,0,C113/$C$114) -> 0 | E113: =E111-E112 -> 0 | F113: =IF($E$114=0,0,E113/$E$114) -> 0 | G113: =G111-G112 -> 0 | H113: =IF($G$114=0,0,G113/$G$114) -> 0 | I113: =I111-I112 -> 0 | J113: =IF($I$114=0,0,I113/$I$114) -> 0
B114: Custos | C114: =SUM(C115:C118) -> 0 | D114: =IF($C$114=0,0,C114/$C$114) -> 0 | E114: =SUM(E115:E118) -> 0 | F114: =IF($E$114=0,0,E114/$E$114) -> 0 | G114: =SUM(G115:G118) -> 0 | H114: =IF($G$114=0,0,G114/$G$114) -> 0 | I114: =SUM(I115:I118) -> 0 | J114: =IF($I$114=0,0,I114/$I$114) -> 0
B115: - Depreciação/Amortização | D115: =IF($C$114=0,0,C115/$C$114) -> 0 | F115: =IF($E$114=0,0,E115/$E$114) -> 0 | H115: =IF($G$114=0,0,G115/$G$114) -> 0 | J115: =IF($I$114=0,0,I115/$I$114) -> 0
B116: - Depreciação/Amortização Estimada | D116: =IF($C$114=0,0,C116/$C$114) -> 0 | F116: =IF($E$114=0,0,E116/$E$114) -> 0 | H116: =IF($G$114=0,0,G116/$G$114) -> 0 | J116: =IF($I$114=0,0,I116/$I$114) -> 0
B117: - Arrendamento Mercantil | D117: =IF($C$114=0,0,C117/$C$114) -> 0 | F117: =IF($E$114=0,0,E117/$E$114) -> 0 | H117: =IF($G$114=0,0,G117/$G$114) -> 0 | J117: =IF($I$114=0,0,I117/$I$114) -> 0
B118: - Custos Diretos | D118: =IF($C$114=0,0,C118/$C$114) -> 0 | F118: =IF($E$114=0,0,E118/$E$114) -> 0 | H118: =IF($G$114=0,0,G118/$G$114) -> 0 | J118: =IF($I$114=0,0,I118/$I$114) -> 0
B119: RES. BRUTO | C119: =C113-C114 -> 0 | D119: =IF($C$114=0,0,C119/$C$114) -> 0 | E119: =E113-E114 -> 0 | F119: =IF($E$114=0,0,E119/$E$114) -> 0 | G119: =G113-G114 -> 0 | H119: =IF($G$114=0,0,G119/$G$114) -> 0 | I119: =I113-I114 -> 0 | J119: =IF($I$114=0,0,I119/$I$114) -> 0
B120: Desps. Operac. | C120: =SUM(C121:C123) -> 0 | D120: =IF($C$114=0,0,C120/$C$114) -> 0 | E120: =SUM(E121:E123) -> 0 | F120: =IF($E$114=0,0,E120/$E$114) -> 0 | G120: =SUM(G121:G123) -> 0 | H120: =IF($G$114=0,0,G120/$G$114) -> 0 | I120: =SUM(I121:I123) -> 0 | J120: =IF($I$114=0,0,I120/$I$114) -> 0
B121: -Despesas Comerciais | D121: =IF($C$114=0,0,C121/$C$114) -> 0 | F121: =IF($E$114=0,0,E121/$E$114) -> 0 | H121: =IF($G$114=0,0,G121/$G$114) -> 0 | J121: =IF($I$114=0,0,I121/$I$114) -> 0
B122: -Despesas Administrativas | D122: =IF($C$114=0,0,C122/$C$114) -> 0 | F122: =IF($E$114=0,0,E122/$E$114) -> 0 | H122: =IF($G$114=0,0,G122/$G$114) -> 0 | J122: =IF($I$114=0,0,I122/$I$114) -> 0
B123: -Despesas c/ Depreciação | D123: =IF($C$114=0,0,C123/$C$114) -> 0 | F123: =IF($E$114=0,0,E123/$E$114) -> 0 | H123: =IF($G$114=0,0,G123/$G$114) -> 0 | J123: =IF($I$114=0,0,I123/$I$114) -> 0
B124: RES. ATIVIDADE | C124: =C119-C120 -> 0 | D124: =IF($C$114=0,0,C124/$C$114) -> 0 | E124: =E119-E120 -> 0 | F124: =IF($E$114=0,0,E124/$E$114) -> 0 | G124: =G119-G120 -> 0 | H124: =IF($G$114=0,0,G124/$G$114) -> 0 | I124: =I119-I120 -> 0 | J124: =IF($I$114=0,0,I124/$I$114) -> 0
B125: Despesas/(Receitas) Financ. Líq. | C125: =SUM(C126:C127) -> 0 | D125: =IF($C$114=0,0,C125/$C$114) -> 0 | E125: =SUM(E126:E127) -> 0 | F125: =IF($E$114=0,0,E125/$E$114) -> 0 | G125: =SUM(G126:G127) -> 0 | H125: =IF($G$114=0,0,G125/$G$114) -> 0 | I125: =SUM(I126:I127) -> 0 | J125: =IF($I$114=0,0,I125/$I$114) -> 0
B126: - Despesas Financeiras | D126: =IF($C$114=0,0,C126/$C$114) -> 0 | F126: =IF($E$114=0,0,E126/$E$114) -> 0 | H126: =IF($G$114=0,0,G126/$G$114) -> 0 | J126: =IF($I$114=0,0,I126/$I$114) -> 0
B127: - Receitas Financeiras | D127: =IF($C$114=0,0,C127/$C$114) -> 0 | F127: =IF($E$114=0,0,E127/$E$114) -> 0 | H127: =IF($G$114=0,0,G127/$G$114) -> 0 | J127: =IF($I$114=0,0,I127/$I$114) -> 0
B128: Variações Monetárias Líq. LP | D128: =IF($C$114=0,0,C128/$C$114) -> 0 | F128: =IF($E$114=0,0,E128/$E$114) -> 0 | H128: =IF($G$114=0,0,G128/$G$114) -> 0 | J128: =IF($I$114=0,0,I128/$I$114) -> 0
B129: Outras Rec./(Desp.) Operac. | D129: =IF($C$114=0,0,C129/$C$114) -> 0 | F129: =IF($E$114=0,0,E129/$E$114) -> 0 | H129: =IF($G$114=0,0,G129/$G$114) -> 0 | J129: =IF($I$114=0,0,I129/$I$114) -> 0
B130: RES. OPERACIONAL | C130: =C124-C125+C128+C129 -> 0 | D130: =IF($C$114=0,0,C130/$C$114) -> 0 | E130: =E124-E125+E128+E129 -> 0 | F130: =IF($E$114=0,0,E130/$E$114) -> 0 | G130: =G124-G125+G128+G129 -> 0 | H130: =IF($G$114=0,0,G130/$G$114) -> 0 | I130: =I124-I125+I128+I129 -> 0 | J130: =IF($I$114=0,0,I130/$I$114) -> 0
B131: Equivalência Patrimonial | D131: =IF($C$114=0,0,C131/$C$114) -> 0 | F131: =IF($E$114=0,0,E131/$E$114) -> 0 | H131: =IF($G$114=0,0,G131/$G$114) -> 0 | J131: =IF($I$114=0,0,I131/$I$114) -> 0
B132: Res. não Operacional | D132: =IF($C$114=0,0,C132/$C$114) -> 0 | F132: =IF($E$114=0,0,E132/$E$114) -> 0 | H132: =IF($G$114=0,0,G132/$G$114) -> 0 | J132: =IF($I$114=0,0,I132/$I$114) -> 0
B133: Correção Monetária | D133: =IF($C$114=0,0,C133/$C$114) -> 0 | F133: =IF($E$114=0,0,E133/$E$114) -> 0 | H133: =IF($G$114=0,0,G133/$G$114) -> 0 | J133: =IF($I$114=0,0,I133/$I$114) -> 0
...

Sheet CONSOLIDADO
B1: TOTAL ATIVO | C1: =SUM(C11+C29+C42) -> 0 | E1: =SUM(E11+E29+E42) -> 0 | G1: =SUM(G11+G29+G42) -> 0 | I1: =SUM(I11+I29+I42) -> 0
B2: TOTAL PASSIVO | C2: =C51+C79+C97+C99+C101 -> 0 | E2: =E51+E79+E97+E99+E101 -> 0 | G2: =G51+G79+G97+G99+G101 -> 0 | I2: =I51+I79+I97+I99+I101 -> 0
B3: DIFERENÇA | C3: =C1-C2 -> 0 | E3: =E1-E2 -> 0 | G3: =G1-G2 -> 0 | I3: =I1-I2 -> 0
B5: GRUPO ECONOMICO 1
B7: BALANÇO PATRIMONIAL
C8: 44896 | E8: 45261 | G8: 45627 | I8: 45992
B9: ATIVO | C9: R$ MIL | D9: (%) | E9: R$ MIL | F9: (%) | G9: R$ MIL | H9: (%) | I9: R$ MIL | J9: (%)
B11: CIRCULANTE | C11: =SUM(C12:C27) -> 0 | D11: =IF($D$48="ERRO","ERRO",IF($D$48=0,0,C11/$D$48)) -> 0 | E11: =SUM(E12:E27) -> 0 | F11: =IF($F$48="ERRO","ERRO",IF($F$48=0,0,E11/$F$48)) -> 0 | G11: =SUM(G12:G27) -> 0 | H11: =IF($H$48="ERRO","ERRO",IF($H$48=0,0,G11/$H$48)) -> 0 | I11: =SUM(I12:I27) -> 0 | J11: =IF($J$48="ERRO","ERRO",IF($J$48=0,0,I11/$J$48)) -> 0
B12: Caixa e Bancos | C12: =SUM(EMP_1!C12+EMP_2!C12) -> 0 | D12: =IF($D$48="ERRO","ERRO",IF($D$48=0,0,C12/$D$48)) -> 0 | E12: =SUM(EMP_1!E12+EMP_2!E12) -> 0 | F12: =IF($F$48="ERRO","ERRO",IF($F$48=0,0,E12/$F$48)) -> 0 | G12: =SUM(EMP_1!G12+EMP_2!G12) -> 0 | H12: =IF($H$48="ERRO","ERRO",IF($H$48=0,0,G12/$H$48)) -> 0 | I12: =SUM(EMP_1!I12+EMP_2!I12) -> 0 | J12: =IF($J$48="ERRO","ERRO",IF($J$48=0,0,I12/$J$48)) -> 0
B13: Aplicações Financeiras | C13: =SUM(EMP_1!C13+EMP_2!C13) -> 0 | D13: =IF($D$48="ERRO","ERRO",IF($D$48=0,0,C13/$D$48)) -> 0 | E13: =SUM(EMP_1!E13+EMP_2!E13) -> 0 | F13: =IF($F$48="ERRO","ERRO",IF($F$48=0,0,E13/$F$48)) -> 0 | G13: =SUM(EMP_1!G13+EMP_2!G13) -> 0 | H13: =IF($H$48="ERRO","ERRO",IF($H$48=0,0,G13/$H$48)) -> 0 | I13: =SUM(EMP_1!I13+EMP_2!I13) -> 0 | J13: =IF($J$48="ERRO","ERRO",IF($J$48=0,0,I13/$J$48)) -> 0
B14: Contas a Receber | C14: 0 | D14: =IF($D$48="ERRO","ERRO",IF($D$48=0,0,C14/$D$48)) -> 0 | E14: 0 | F14: =IF($F$48="ERRO","ERRO",IF($F$48=0,0,E14/$F$48)) -> 0 | G14: =SUM(EMP_1!G14+EMP_2!G14) -> 0 | H14: =IF($H$48="ERRO","ERRO",IF($H$48=0,0,G14/$H$48)) -> 0 | I14: =SUM(EMP_1!I14+EMP_2!I14) -> 0 | J14: =IF($J$48="ERRO","ERRO",IF($J$48=0,0,I14/$J$48)) -> 0
B15: Cooperados | C15: =SUM(EMP_1!C15+EMP_2!C15) -> 0 | D15: =IF($D$48="ERRO","ERRO",IF($D$48=0,0,C15/$D$48)) -> 0 | E15: =SUM(EMP_1!E15+EMP_2!E15) -> 0 | F15: =IF($F$48="ERRO","ERRO",IF($F$48=0,0,E15/$F$48)) -> 0 | G15: =SUM(EMP_1!G15+EMP_2!G15) -> 0 | H15: =IF($H$48="ERRO","ERRO",IF($H$48=0,0,G15/$H$48)) -> 0 | I15: =SUM(EMP_1!I15+EMP_2!I15) -> 0 | J15: =IF($J$48="ERRO","ERRO",IF($J$48=0,0,I15/$J$48)) -> 0
B16: CVA | C16: =SUM(EMP_1!C16+EMP_2!C16) -> 0 | D16: =IF($D$48="ERRO","ERRO",IF($D$48=0,0,C16/$D$48)) -> 0 | E16: =SUM(EMP_1!E16+EMP_2!E16) -> 0 | F16: =IF($F$48="ERRO","ERRO",IF($F$48=0,0,E16/$F$48)) -> 0 | G16: =SUM(EMP_1!G16+EMP_2!G16) -> 0 | H16: =IF($H$48="ERRO","ERRO",IF($H$48=0,0,G16/$H$48)) -> 0 | I16: =SUM(EMP_1!I16+EMP_2!I16) -> 0 | J16: =IF($J$48="ERRO","ERRO",IF($J$48=0,0,I16/$J$48)) -> 0
B17: Estoques | C17: =SUM(EMP_1!C17+EMP_2!C17) -> 0 | D17: =IF($D$48="ERRO","ERRO",IF($D$48=0,0,C17/$D$48)) -> 0 | E17: =SUM(EMP_1!E17+EMP_2!E17) -> 0 | F17: =IF($F$48="ERRO","ERRO",IF($F$48=0,0,E17/$F$48)) -> 0 | G17: =SUM(EMP_1!G17+EMP_2!G17) -> 0 | H17: =IF($H$48="ERRO","ERRO",IF($H$48=0,0,G17/$H$48)) -> 0 | I17: =SUM(EMP_1!I17+EMP_2!I17) -> 0 | J17: =IF($J$48="ERRO","ERRO",IF($J$48=0,0,I17/$J$48)) -> 0
B18: Adiant. a Fornecedores | C18: =SUM(EMP_1!C18+EMP_2!C18) -> 0 | D18: =IF($D$48="ERRO","ERRO",IF($D$48=0,0,C18/$D$48)) -> 0 | E18: =SUM(EMP_1!E18+EMP_2!E18) -> 0 | F18: =IF($F$48="ERRO","ERRO",IF($F$48=0,0,E18/$F$48)) -> 0 | G18: =SUM(EMP_1!G18+EMP_2!G18) -> 0 | H18: =IF($H$48="ERRO","ERRO",IF($H$48=0,0,G18/$H$48)) -> 0 | I18: =SUM(EMP_1!I18+EMP_2!I18) -> 0 | J18: =IF($J$48="ERRO","ERRO",IF($J$48=0,0,I18/$J$48)) -> 0
B19: Créditos a Fumicultores | C19: =SUM(EMP_1!C19+EMP_2!C19) -> 0 | D19: =IF($D$48="ERRO","ERRO",IF($D$48=0,0,C19/$D$48)) -> 0 | E19: =SUM(EMP_1!E19+EMP_2!E19) -> 0 | F19: =IF($F$48="ERRO","ERRO",IF($F$48=0,0,E19/$F$48)) -> 0 | G19: =SUM(EMP_1!G19+EMP_2!G19) -> 0 | H19: =IF($H$48="ERRO","ERRO",IF($H$48=0,0,G19/$H$48)) -> 0 | I19: =SUM(EMP_1!I19+EMP_2!I19) -> 0 | J19: =IF($J$48="ERRO","ERRO",IF($J$48=0,0,I19/$J$48)) -> 0
B20: Despesas Antecipadas | C20: =SUM(EMP_1!C20+EMP_2!C20) -> 0 | D20: =IF($D$48="ERRO","ERRO",IF($D$48=0,0,C20/$D$48)) -> 0 | E20: =SUM(EMP_1!E20+EMP_2!E20) -> 0 | F20: =IF($F$48="ERRO","ERRO",IF($F$48=0,0,E20/$F$48)) -> 0 | G20: =SUM(EMP_1!G20+EMP_2!G20) -> 0 | H20: =IF($H$48="ERRO","ERRO",IF($H$48=0,0,G20/$H$48)) -> 0 | I20: =SUM(EMP_1!I20+EMP_2!I20) -> 0 | J20: =IF($J$48="ERRO","ERRO",IF($J$48=0,0,I20/$J$48)) -> 0
B21: Impostos a Recuperar | C21: =SUM(EMP_1!C21+EMP_2!C21) -> 0 | D21: =IF($D$48="ERRO","ERRO",IF($D$48=0,0,C21/$D$48)) -> 0 | E21: =SUM(EMP_1!E21+EMP_2!E21) -> 0 | F21: =IF($F$48="ERRO","ERRO",IF($F$48=0,0,E21/$F$48)) -> 0 | G21: =SUM(EMP_1!G21+EMP_2!G21) -> 0 | H21: =IF($H$48="ERRO","ERRO",IF($H$48=0,0,G21/$H$48)) -> 0 | I21: =SUM(EMP_1!I21+EMP_2!I21) -> 0 | J21: =IF($J$48="ERRO","ERRO",IF($J$48=0,0,I21/$J$48)) -> 0
B22: Dividendos a Receber | C22: =SUM(EMP_1!C22+EMP_2!C22) -> 0 | D22: =IF($D$48="ERRO","ERRO",IF($D$48=0,0,C22/$D$48)) -> 0 | E22: =SUM(EMP_1!E22+EMP_2!E22) -> 0 | F22: =IF($F$48="ERRO","ERRO",IF($F$48=0,0,E22/$F$48)) -> 0 | G22: =SUM(EMP_1!G22+EMP_2!G22) -> 0 | H22: =IF($H$48="ERRO","ERRO",IF($H$48=0,0,G22/$H$48)) -> 0 | I22: =SUM(EMP_1!I22+EMP_2!I22) -> 0 | J22: =IF($J$48="ERRO","ERRO",IF($J$48=0,0,I22/$J$48)) -> 0
B23: Imposto Diferido | C23: =SUM(EMP_1!C23+EMP_2!C23) -> 0 | D23: =IF($D$48="ERRO","ERRO",IF($D$48=0,0,C23/$D$48)) -> 0 | E23: =SUM(EMP_1!E23+EMP_2!E23) -> 0 | F23: =IF($F$48="ERRO","ERRO",IF($F$48=0,0,E23/$F$48)) -> 0 | G23: =SUM(EMP_1!G23+EMP_2!G23) -> 0 | H23: =IF($H$48="ERRO","ERRO",IF($H$48=0,0,G23/$H$48)) -> 0 | I23: =SUM(EMP_1!I23+EMP_2!I23) -> 0 | J23: =IF($J$48="ERRO","ERRO",IF($J$48=0,0,I23/$J$48)) -> 0
B24: Outros Operac. | C24: =SUM(EMP_1!C24+EMP_2!C24) -> 0 | D24: =IF($D$48="ERRO","ERRO",IF($D$48=0,0,C24/$D$48)) -> 0 | E24: =SUM(EMP_1!E24+EMP_2!E24) -> 0 | F24: =IF($F$48="ERRO","ERRO",IF($F$48=0,0,E24/$F$48)) -> 0 | G24: =SUM(EMP_1!G24+EMP_2!G24) -> 0 | H24: =IF($H$48="ERRO","ERRO",IF($H$48=0,0,G24/$H$48)) -> 0 | I24: =SUM(EMP_1!I24+EMP_2!I24) -> 0 | J24: =IF($J$48="ERRO","ERRO",IF($J$48=0,0,I24/$J$48)) -> 0
B25: Outros Operac. | C25: =SUM(EMP_1!C25+EMP_2!C25) -> 0 | D25: =IF($D$48="ERRO","ERRO",IF($D$48=0,0,C25/$D$48)) -> 0 | E25: =SUM(EMP_1!E25+EMP_2!E25) -> 0 | F25: =IF($F$48="ERRO","ERRO",IF($F$48=0,0,E25/$F$48)) -> 0 | G25: =SUM(EMP_1!G25+EMP_2!G25) -> 0 | H25: =IF($H$48="ERRO","ERRO",IF($H$48=0,0,G25/$H$48)) -> 0 | I25: =SUM(EMP_1!I25+EMP_2!I25) -> 0 | J25: =IF($J$48="ERRO","ERRO",IF($J$48=0,0,I25/$J$48)) -> 0
B26: Outros Nao Operac. | C26: =SUM(EMP_1!C26+EMP_2!C26) -> 0 | D26: =IF($D$48="ERRO","ERRO",IF($D$48=0,0,C26/$D$48)) -> 0 | E26: =SUM(EMP_1!E26+EMP_2!E26) -> 0 | F26: =IF($F$48="ERRO","ERRO",IF($F$48=0,0,E26/$F$48)) -> 0 | G26: =SUM(EMP_1!G26+EMP_2!G26) -> 0 | H26: =IF($H$48="ERRO","ERRO",IF($H$48=0,0,G26/$H$48)) -> 0 | I26: =SUM(EMP_1!I26+EMP_2!I26) -> 0 | J26: =IF($J$48="ERRO","ERRO",IF($J$48=0,0,I26/$J$48)) -> 0
B27: Outros Nao Operac. | C27: =SUM(EMP_1!C27+EMP_2!C27) -> 0 | D27: =IF($D$48="ERRO","ERRO",IF($D$48=0,0,C27/$D$48)) -> 0 | E27: =SUM(EMP_1!E27+EMP_2!E27) -> 0 | F27: =IF($F$48="ERRO","ERRO",IF($F$48=0,0,E27/$F$48)) -> 0 | G27: =SUM(EMP_1!G27+EMP_2!G27) -> 0 | H27: =IF($H$48="ERRO","ERRO",IF($H$48=0,0,G27/$H$48)) -> 0 | I27: =SUM(EMP_1!I27+EMP_2!I27) -> 0 | J27: =IF($J$48="ERRO","ERRO",IF($J$48=0,0,I27/$J$48)) -> 0
B29: REALIZ. L.P. | C29: =SUM(C30:C40) -> 0 | D29: =IF($D$48="ERRO","ERRO",IF($D$48=0,0,C29/$D$48)) -> 0 | E29: =SUM(E30:E40) -> 0 | F29: =IF($F$48="ERRO","ERRO",IF($F$48=0,0,E29/$F$48)) -> 0 | G29: =SUM(G30:G40) -> 0 | H29: =IF($H$48="ERRO","ERRO",IF($H$48=0,0,G29/$H$48)) -> 0 | I29: =SUM(I30:I40) -> 0 | J29: =IF($J$48="ERRO","ERRO",IF($J$48=0,0,I29/$J$48)) -> 0
B30: Contas a Receber | C30: =SUM(EMP_1!C30+EMP_2!C30) -> 0 | D30: =IF($D$48="ERRO","ERRO",IF($D$48=0,0,C30/$D$48)) -> 0 | E30: =SUM(EMP_1!E30+EMP_2!E30) -> 0 | F30: =IF($F$48="ERRO","ERRO",IF($F$48=0,0,E30/$F$48)) -> 0 | G30: =SUM(EMP_1!G30+EMP_2!G30) -> 0 | H30: =IF($H$48="ERRO","ERRO",IF($H$48=0,0,G30/$H$48)) -> 0 | I30: =SUM(EMP_1!I30+EMP_2!I30) -> 0 | J30: =IF($J$48="ERRO","ERRO",IF($J$48=0,0,I30/$J$48)) -> 0
B31: Cooperados | C31: =SUM(EMP_1!C31+EMP_2!C31) -> 0 | D31: =IF($D$48="ERRO","ERRO",IF($D$48=0,0,C31/$D$48)) -> 0 | E31: =SUM(EMP_1!E31+EMP_2!E31) -> 0 | F31: =IF($F$48="ERRO","ERRO",IF($F$48=0,0,E31/$F$48)) -> 0 | G31: =SUM(EMP_1!G31+EMP_2!G31) -> 0 | H31: =IF($H$48="ERRO","ERRO",IF($H$48=0,0,G31/$H$48)) -> 0 | I31: =SUM(EMP_1!I31+EMP_2!I31) -> 0 | J31: =IF($J$48="ERRO","ERRO",IF($J$48=0,0,I31/$J$48)) -> 0
B32: C/C Coligadas/Acionistas | C32: =SUM(EMP_1!C32+EMP_2!C32) -> 0 | D32: =IF($D$48="ERRO","ERRO",IF($D$48=0,0,C32/$D$48)) -> 0 | E32: =SUM(EMP_1!E32+EMP_2!E32) -> 0 | F32: =IF($F$48="ERRO","ERRO",IF($F$48=0,0,E32/$F$48)) -> 0 | G32: =SUM(EMP_1!G32+EMP_2!G32) -> 0 | H32: =IF($H$48="ERRO","ERRO",IF($H$48=0,0,G32/$H$48)) -> 0 | I32: =SUM(EMP_1!I32+EMP_2!I32) -> 0 | J32: =IF($J$48="ERRO","ERRO",IF($J$48=0,0,I32/$J$48)) -> 0
B33: Depósitos Judiciais | C33: =SUM(EMP_1!C33+EMP_2!C33) -> 0 | D33: =IF($D$48="ERRO","ERRO",IF($D$48=0,0,C33/$D$48)) -> 0 | E33: =SUM(EMP_1!E33+EMP_2!E33) -> 0 | F33: =IF($F$48="ERRO","ERRO",IF($F$48=0,0,E33/$F$48)) -> 0 | G33: =SUM(EMP_1!G33+EMP_2!G33) -> 0 | H33: =IF($H$48="ERRO","ERRO",IF($H$48=0,0,G33/$H$48)) -> 0 | I33: =SUM(EMP_1!I33+EMP_2!I33) -> 0 | J33: =IF($J$48="ERRO","ERRO",IF($J$48=0,0,I33/$J$48)) -> 0
B34: Imposto Diferido | C34: =SUM(EMP_1!C34+EMP_2!C34) -> 0 | D34: =IF($D$48="ERRO","ERRO",IF($D$48=0,0,C34/$D$48)) -> 0 | E34: =SUM(EMP_1!E34+EMP_2!E34) -> 0 | F34: =IF($F$48="ERRO","ERRO",IF($F$48=0,0,E34/$F$48)) -> 0 | G34: =SUM(EMP_1!G34+EMP_2!G34) -> 0 | H34: =IF($H$48="ERRO","ERRO",IF($H$48=0,0,G34/$H$48)) -> 0 | I34: =SUM(EMP_1!I34+EMP_2!I34) -> 0 | J34: =IF($J$48="ERRO","ERRO",IF($J$48=0,0,I34/$J$48)) -> 0
B35: Créditos a Fumicultores | C35: =SUM(EMP_1!C35+EMP_2!C35) -> 0 | D35: =IF($D$48="ERRO","ERRO",IF($D$48=0,0,C35/$D$48)) -> 0 | E35: =SUM(EMP_1!E35+EMP_2!E35) -> 0 | F35: =IF($F$48="ERRO","ERRO",IF($F$48=0,0,E35/$F$48)) -> 0 | G35: =SUM(EMP_1!G35+EMP_2!G35) -> 0 | H35: =IF($H$48="ERRO","ERRO",IF($H$48=0,0,G35/$H$48)) -> 0 | I35: =SUM(EMP_1!I35+EMP_2!I35) -> 0 | J35: =IF($J$48="ERRO","ERRO",IF($J$48=0,0,I35/$J$48)) -> 0
B36: CTN´s | C36: =SUM(EMP_1!C36+EMP_2!C36) -> 0 | D36: =IF($D$48="ERRO","ERRO",IF($D$48=0,0,C36/$D$48)) -> 0 | E36: =SUM(EMP_1!E36+EMP_2!E36) -> 0 | F36: =IF($F$48="ERRO","ERRO",IF($F$48=0,0,E36/$F$48)) -> 0 | G36: =SUM(EMP_1!G36+EMP_2!G36) -> 0 | H36: =IF($H$48="ERRO","ERRO",IF($H$48=0,0,G36/$H$48)) -> 0 | I36: =SUM(EMP_1!I36+EMP_2!I36) -> 0 | J36: =IF($J$48="ERRO","ERRO",IF($J$48=0,0,I36/$J$48)) -> 0
B37: Outros Operac. | C37: =SUM(EMP_1!C37+EMP_2!C37) -> 0 | D37: =IF($D$48="ERRO","ERRO",IF($D$48=0,0,C37/$D$48)) -> 0 | E37: =SUM(EMP_1!E37+EMP_2!E37) -> 0 | F37: =IF($F$48="ERRO","ERRO",IF($F$48=0,0,E37/$F$48)) -> 0 | G37: =SUM(EMP_1!G37+EMP_2!G37) -> 0 | H37: =IF($H$48="ERRO","ERRO",IF($H$48=0,0,G37/$H$48)) -> 0 | I37: =SUM(EMP_1!I37+EMP_2!I37) -> 0 | J37: =IF($J$48="ERRO","ERRO",IF($J$48=0,0,I37/$J$48)) -> 0
B38: Outros Operac. | C38: =SUM(EMP_1!C38+EMP_2!C38) -> 0 | D38: =IF($D$48="ERRO","ERRO",IF($D$48=0,0,C38/$D$48)) -> 0 | E38: =SUM(EMP_1!E38+EMP_2!E38) -> 0 | F38: =IF($F$48="ERRO","ERRO",IF($F$48=0,0,E38/$F$48)) -> 0 | G38: =SUM(EMP_1!G38+EMP_2!G38) -> 0 | H38: =IF($H$48="ERRO","ERRO",IF($H$48=0,0,G38/$H$48)) -> 0 | I38: =SUM(EMP_1!I38+EMP_2!I38) -> 0 | J38: =IF($J$48="ERRO","ERRO",IF($J$48=0,0,I38/$J$48)) -> 0
B39: Outros Nao Operac. | C39: =SUM(EMP_1!C39+EMP_2!C39) -> 0 | D39: =IF($D$48="ERRO","ERRO",IF($D$48=0,0,C39/$D$48)) -> 0 | E39: =SUM(EMP_1!E39+EMP_2!E39) -> 0 | F39: =IF($F$48="ERRO","ERRO",IF($F$48=0,0,E39/$F$48)) -> 0 | G39: =SUM(EMP_1!G39+EMP_2!G39) -> 0 | H39: =IF($H$48="ERRO","ERRO",IF($H$48=0,0,G39/$H$48)) -> 0 | I39: =SUM(EMP_1!I39+EMP_2!I39) -> 0 | J39: =IF($J$48="ERRO","ERRO",IF($J$48=0,0,I39/$J$48)) -> 0
B40: Outros Nao Operac. | C40: =SUM(EMP_1!C40+EMP_2!C40) -> 0 | D40: =IF($D$48="ERRO","ERRO",IF($D$48=0,0,C40/$D$48)) -> 0 | E40: =SUM(EMP_1!E40+EMP_2!E40) -> 0 | F40: =IF($F$48="ERRO","ERRO",IF($F$48=0,0,E40/$F$48)) -> 0 | G40: =SUM(EMP_1!G40+EMP_2!G40) -> 0 | H40: =IF($H$48="ERRO","ERRO",IF($H$48=0,0,G40/$H$48)) -> 0 | I40: =SUM(EMP_1!I40+EMP_2!I40) -> 0 | J40: =IF($J$48="ERRO","ERRO",IF($J$48=0,0,I40/$J$48)) -> 0
B42: PERMANENTE | C42: =SUM(C43:C45) -> 0 | D42: =IF($D$48="ERRO","ERRO",IF($D$48=0,0,C42/$D$48)) -> 0 | E42: =SUM(E43:E45) -> 0 | F42: =IF($F$48="ERRO","ERRO",IF($F$48=0,0,E42/$F$48)) -> 0 | G42: =SUM(G43:G45) -> 0 | H42: =IF($H$48="ERRO","ERRO",IF($H$48=0,0,G42/$H$48)) -> 0 | I42: =SUM(I43:I45) -> 0 | J42: =IF($J$48="ERRO","ERRO",IF($J$48=0,0,I42/$J$48)) -> 0
B43: Imobilizado Técnico | C43: =SUM(EMP_1!C43+EMP_2!C43) -> 0 | D43: =IF($D$48="ERRO","ERRO",IF($D$48=0,0,C43/$D$48)) -> 0 | E43: =SUM(EMP_1!E43+EMP_2!E43) -> 0 | F43: =IF($F$48="ERRO","ERRO",IF($F$48=0,0,E43/$F$48)) -> 0 | G43: =SUM(EMP_1!G43+EMP_2!G43) -> 0 | H43: =IF($H$48="ERRO","ERRO",IF($H$48=0,0,G43/$H$48)) -> 0 | I43: =SUM(EMP_1!I43+EMP_2!I43) -> 0 | J43: =IF($J$48="ERRO","ERRO",IF($J$48=0,0,I43/$J$48)) -> 0
B44: Investimentos | C44: =SUM(EMP_1!C44+EMP_2!C44) -> 0 | D44: =IF($D$48="ERRO","ERRO",IF($D$48=0,0,C44/$D$48)) -> 0 | E44: =SUM(EMP_1!E44+EMP_2!E44) -> 0 | F44: =IF($F$48="ERRO","ERRO",IF($F$48=0,0,E44/$F$48)) -> 0 | G44: =SUM(EMP_1!G44+EMP_2!G44) -> 0 | H44: =IF($H$48="ERRO","ERRO",IF($H$48=0,0,G44/$H$48)) -> 0 | I44: =SUM(EMP_1!I44+EMP_2!I44) -> 0 | J44: =IF($J$48="ERRO","ERRO",IF($J$48=0,0,I44/$J$48)) -> 0
B45: Diferido/Intangível | C45: =SUM(EMP_1!C45+EMP_2!C45) -> 0 | D45: =IF($D$48="ERRO","ERRO",IF($D$48=0,0,C45/$D$48)) -> 0 | E45: =SUM(EMP_1!E45+EMP_2!E45) -> 0 | F45: =IF($F$48="ERRO","ERRO",IF($F$48=0,0,E45/$F$48)) -> 0 | G45: =SUM(EMP_1!G45+EMP_2!G45) -> 0 | H45: =IF($H$48="ERRO","ERRO",IF($H$48=0,0,G45/$H$48)) -> 0 | I45: =SUM(EMP_1!I45+EMP_2!I45) -> 0 | J45: =IF($J$48="ERRO","ERRO",IF($J$48=0,0,I45/$J$48)) -> 0
B47: TOTAL | C47: =IF(OR(C11+C29+C42-C51-C79-C97-C99-C101>1,C11+C29+C42-C51-C79-C97-C99-C101<-1),"ERRO",C11+C29+C42) -> 0 | D47: =IF($D$48="ERRO","ERRO",IF($D$48=0,0,C47/$D$48)) -> 0 | E47: =IF(OR(E11+E29+E42-E51-E79-E97-E99-E101>1,E11+E29+E42-E51-E79-E97-E99-E101<-1),"ERRO",E11+E29+E42) -> 0 | F47: =IF($F$48="ERRO","ERRO",IF($F$48=0,0,E47/$F$48)) -> 0 | G47: =IF(OR(G11+G29+G42-G51-G79-G97-G99-G101>1,G11+G29+G42-G51-G79-G97-G99-G101<-1),"ERRO",G11+G29+G42) -> 0 | H47: =IF($H$48="ERRO","ERRO",IF($H$48=0,0,G47/$H$48)) -> 0 | I47: =IF(OR(I11+I29+I42-I51-I79-I97-I99-I101>1,I11+I29+I42-I51-I79-I97-I99-I101<-1),"ERRO",I11+I29+I42) -> 0 | J47: =IF($J$48="ERRO","ERRO",IF($J$48=0,0,I47/$J$48)) -> 0
B49: PASSIVO | C49: R$ MIL | D49: (%) | E49: R$ MIL | F49: (%) | G49: R$ MIL | H49: (%) | I49: R$ MIL | J49: (%)
B51: CIRCULANTE | C51: =SUM(C52:C77) -> 0 | D51: =IF($D$48="ERRO","ERRO",IF($D$48=0,0,C51/$D$48)) -> 0 | E51: =SUM(E52:E77) -> 0 | F51: =IF($F$48="ERRO","ERRO",IF($F$48=0,0,E51/$F$48)) -> 0 | G51: =SUM(G52:G77) -> 0 | H51: =IF($H$48="ERRO","ERRO",IF($H$48=0,0,G51/$H$48)) -> 0 | I51: =SUM(I52:I77) -> 0 | J51: =IF($J$48="ERRO","ERRO",IF($J$48=0,0,I51/$J$48)) -> 0
B52: Fornecedores Nacionais | C52: =SUM(EMP_1!C52+EMP_2!C52) -> 0 | D52: =IF($D$48="ERRO","ERRO",IF($D$48=0,0,C52/$D$48)) -> 0 | E52: =SUM(EMP_1!E52+EMP_2!E52) -> 0 | F52: =IF($F$48="ERRO","ERRO",IF($F$48=0,0,E52/$F$48)) -> 0 | G52: =SUM(EMP_1!G52+EMP_2!G52) -> 0 | H52: =IF($H$48="ERRO","ERRO",IF($H$48=0,0,G52/$H$48)) -> 0 | I52: =SUM(EMP_1!I52+EMP_2!I52) -> 0 | J52: =IF($J$48="ERRO","ERRO",IF($J$48=0,0,I52/$J$48)) -> 0
B53: Fornecedores Estrangeiros | C53: =SUM(EMP_1!C53+EMP_2!C53) -> 0 | D53: =IF($D$48="ERRO","ERRO",IF($D$48=0,0,C53/$D$48)) -> 0 | E53: =SUM(EMP_1!E53+EMP_2!E53) -> 0 | F53: =IF($F$48="ERRO","ERRO",IF($F$48=0,0,E53/$F$48)) -> 0 | G53: =SUM(EMP_1!G53+EMP_2!G53) -> 0 | H53: =IF($H$48="ERRO","ERRO",IF($H$48=0,0,G53/$H$48)) -> 0 | I53: =SUM(EMP_1!I53+EMP_2!I53) -> 0 | J53: =IF($J$48="ERRO","ERRO",IF($J$48=0,0,I53/$J$48)) -> 0
B54: Empréstimos Bancários | C54: =SUM(EMP_1!C54+EMP_2!C54) -> 0 | D54: =IF($D$48="ERRO","ERRO",IF($D$48=0,0,C54/$D$48)) -> 0 | E54: =SUM(EMP_1!E54+EMP_2!E54) -> 0 | F54: =IF($F$48="ERRO","ERRO",IF($F$48=0,0,E54/$F$48)) -> 0 | G54: =SUM(EMP_1!G54+EMP_2!G54) -> 0 | H54: =IF($H$48="ERRO","ERRO",IF($H$48=0,0,G54/$H$48)) -> 0 | I54: =SUM(EMP_1!I54+EMP_2!I54) -> 0 | J54: =IF($J$48="ERRO","ERRO",IF($J$48=0,0,I54/$J$48)) -> 0
B55: Financiamentos Operacionais | C55: =SUM(EMP_1!C55+EMP_2!C55) -> 0 | D55: =IF($D$48="ERRO","ERRO",IF($D$48=0,0,C55/$D$48)) -> 0 | E55: =SUM(EMP_1!E55+EMP_2!E55) -> 0 | F55: =IF($F$48="ERRO","ERRO",IF($F$48=0,0,E55/$F$48)) -> 0 | G55: =SUM(EMP_1!G55+EMP_2!G55) -> 0 | H55: =IF($H$48="ERRO","ERRO",IF($H$48=0,0,G55/$H$48)) -> 0 | I55: =SUM(EMP_1!I55+EMP_2!I55) -> 0 | J55: =IF($J$48="ERRO","ERRO",IF($J$48=0,0,I55/$J$48)) -> 0
B56: Financiamentos c/ Tradings | C56: =SUM(EMP_1!C56+EMP_2!C56) -> 0 | D56: =IF($D$48="ERRO","ERRO",IF($D$48=0,0,C56/$D$48)) -> 0 | E56: =SUM(EMP_1!E56+EMP_2!E56) -> 0 | F56: =IF($F$48="ERRO","ERRO",IF($F$48=0,0,E56/$F$48)) -> 0 | G56: =SUM(EMP_1!G56+EMP_2!G56) -> 0 | H56: =IF($H$48="ERRO","ERRO",IF($H$48=0,0,G56/$H$48)) -> 0 | I56: =SUM(EMP_1!I56+EMP_2!I56) -> 0 | J56: =IF($J$48="ERRO","ERRO",IF($J$48=0,0,I56/$J$48)) -> 0
B57: Parcelas Correntes Financ. L.P. | C57: =SUM(EMP_1!C57+EMP_2!C57) -> 0 | D57: =IF($D$48="ERRO","ERRO",IF($D$48=0,0,C57/$D$48)) -> 0 | E57: =SUM(EMP_1!E57+EMP_2!E57) -> 0 | F57: =IF($F$48="ERRO","ERRO",IF($F$48=0,0,E57/$F$48)) -> 0 | G57: =SUM(EMP_1!G57+EMP_2!G57) -> 0 | H57: =IF($H$48="ERRO","ERRO",IF($H$48=0,0,G57/$H$48)) -> 0 | I57: =SUM(EMP_1!I57+EMP_2!I57) -> 0 | J57: =IF($J$48="ERRO","ERRO",IF($J$48=0,0,I57/$J$48)) -> 0
B58: Debêntures | C58: =SUM(EMP_1!C58+EMP_2!C58) -> 0 | D58: =IF($D$48="ERRO","ERRO",IF($D$48=0,0,C58/$D$48)) -> 0 | E58: =SUM(EMP_1!E58+EMP_2!E58) -> 0 | F58: =IF($F$48="ERRO","ERRO",IF($F$48=0,0,E58/$F$48)) -> 0 | G58: =SUM(EMP_1!G58+EMP_2!G58) -> 0 | H58: =IF($H$48="ERRO","ERRO",IF($H$48=0,0,G58/$H$48)) -> 0 | I58: =SUM(EMP_1!I58+EMP_2!I58) -> 0 | J58: =IF($J$48="ERRO","ERRO",IF($J$48=0,0,I58/$J$48)) -> 0
B59: Swap | C59: =SUM(EMP_1!C59+EMP_2!C59) -> 0 | D59: =IF($D$48="ERRO","ERRO",IF($D$48=0,0,C59/$D$48)) -> 0 | E59: =SUM(EMP_1!E59+EMP_2!E59) -> 0 | F59: =IF($F$48="ERRO","ERRO",IF($F$48=0,0,E59/$F$48)) -> 0 | G59: =SUM(EMP_1!G59+EMP_2!G59) -> 0 | H59: =IF($H$48="ERRO","ERRO",IF($H$48=0,0,G59/$H$48)) -> 0 | I59: =SUM(EMP_1!I59+EMP_2!I59) -> 0 | J59: =IF($J$48="ERRO","ERRO",IF($J$48=0,0,I59/$J$48)) -> 0
B60: Securitização | C60: =SUM(EMP_1!C60+EMP_2!C60) -> 0 | D60: =IF($D$48="ERRO","ERRO",IF($D$48=0,0,C60/$D$48)) -> 0 | E60: =SUM(EMP_1!E60+EMP_2!E60) -> 0 | F60: =IF($F$48="ERRO","ERRO",IF($F$48=0,0,E60/$F$48)) -> 0 | G60: =SUM(EMP_1!G60+EMP_2!G60) -> 0 | H60: =IF($H$48="ERRO","ERRO",IF($H$48=0,0,G60/$H$48)) -> 0 | I60: =SUM(EMP_1!I60+EMP_2!I60) -> 0 | J60: =IF($J$48="ERRO","ERRO",IF($J$48=0,0,I60/$J$48)) -> 0
B61: Leasing | C61: =SUM(EMP_1!C61+EMP_2!C61) -> 0 | D61: =IF($D$48="ERRO","ERRO",IF($D$48=0,0,C61/$D$48)) -> 0 | E61: =SUM(EMP_1!E61+EMP_2!E61) -> 0 | F61: =IF($F$48="ERRO","ERRO",IF($F$48=0,0,E61/$F$48)) -> 0 | G61: =SUM(EMP_1!G61+EMP_2!G61) -> 0 | H61: =IF($H$48="ERRO","ERRO",IF($H$48=0,0,G61/$H$48)) -> 0 | I61: =SUM(EMP_1!I61+EMP_2!I61) -> 0 | J61: =IF($J$48="ERRO","ERRO",IF($J$48=0,0,I61/$J$48)) -> 0
B62: Salários e Encargos | C62: =SUM(EMP_1!C62+EMP_2!C62) -> 0 | D62: =IF($D$48="ERRO","ERRO",IF($D$48=0,0,C62/$D$48)) -> 0 | E62: =SUM(EMP_1!E62+EMP_2!E62) -> 0 | F62: =IF($F$48="ERRO","ERRO",IF($F$48=0,0,E62/$F$48)) -> 0 | G62: =SUM(EMP_1!G62+EMP_2!G62) -> 0 | H62: =IF($H$48="ERRO","ERRO",IF($H$48=0,0,G62/$H$48)) -> 0 | I62: =SUM(EMP_1!I62+EMP_2!I62) -> 0 | J62: =IF($J$48="ERRO","ERRO",IF($J$48=0,0,I62/$J$48)) -> 0
B63: Tributos e Obrigações Fiscais | C63: =SUM(EMP_1!C63+EMP_2!C63) -> 0 | D63: =IF($D$48="ERRO","ERRO",IF($D$48=0,0,C63/$D$48)) -> 0 | E63: =SUM(EMP_1!E63+EMP_2!E63) -> 0 | F63: =IF($F$48="ERRO","ERRO",IF($F$48=0,0,E63/$F$48)) -> 0 | G63: =SUM(EMP_1!G63+EMP_2!G63) -> 0 | H63: =IF($H$48="ERRO","ERRO",IF($H$48=0,0,G63/$H$48)) -> 0 | I63: =SUM(EMP_1!I63+EMP_2!I63) -> 0 | J63: =IF($J$48="ERRO","ERRO",IF($J$48=0,0,I63/$J$48)) -> 0
... B77: Outros Nao Operac. | C77: =SUM(EMP_1!C77+EMP_2!C77) -> 0 | D77: =IF($D$48="ERRO","ERRO",IF($D$48=0,0,C77/$D$48)) -> 0 | E77: =SUM(EMP_1!E77+EMP_2!E77) -> 0 | F77: =IF($F$48="ERRO","ERRO",IF($F$48=0,0,E77/$F$48)) -> 0 | G77: =SUM(EMP_1!G77+EMP_2!G77) -> 0 | H77: =IF($H$48="ERRO","ERRO",IF($H$48=0,0,G77/$H$48)) -> 0 | I77: =SUM(EMP_1!I77+EMP_2!I77) -> 0 | J77: =IF($J$48="ERRO","ERRO",IF($J$48=0,0,I77/$J$48)) -> 0
B79: EXIGÍVEL L.P. | C79: =SUM(C80:C95) -> 0 | D79: =IF($D$48="ERRO","ERRO",IF($D$48=0,0,C79/$D$48)) -> 0 | E79: =SUM(E80:E95) -> 0 | F79: =IF($F$48="ERRO","ERRO",IF($F$48=0,0,E79/$F$48)) -> 0 | G79: =SUM(G80:G95) -> 0 | H79: =IF($H$48="ERRO","ERRO",IF($H$48=0,0,G79/$H$48)) -> 0 | I79: =SUM(I80:I95) -> 0 | J79: =IF($J$48="ERRO","ERRO",IF($J$48=0,0,I79/$J$48)) -> 0
B80: Empréstimos e Financiamentos | C80: =SUM(EMP_1!C80+EMP_2!C80) -> 0 | D80: =IF($D$48="ERRO","ERRO",IF($D$48=0,0,C80/$D$48)) -> 0 | E80: =SUM(EMP_1!E80+EMP_2!E80) -> 0 | F80: =IF($F$48="ERRO","ERRO",IF($F$48=0,0,E80/$F$48)) -> 0 | G80: =SUM(EMP_1!G80+EMP_2!G80) -> 0 | H80: =IF($H$48="ERRO","ERRO",IF($H$48=0,0,G80/$H$48)) -> 0 | I80: =SUM(EMP_1!I80+EMP_2!I80) -> 0 | J80: =IF($J$48="ERRO","ERRO",IF($J$48=0,0,I80/$J$48)) -> 0
B81: Debêntures | C81: =SUM(EMP_1!C81+EMP_2!C81) -> 0 | D81: =IF($D$48="ERRO","ERRO",IF($D$48=0,0,C81/$D$48)) -> 0 | E81: =SUM(EMP_1!E81+EMP_2!E81) -> 0 | F81: =IF($F$48="ERRO","ERRO",IF($F$48=0,0,E81/$F$48)) -> 0 | G81: =SUM(EMP_1!G81+EMP_2!G81) -> 0 | H81: =IF($H$48="ERRO","ERRO",IF($H$48=0,0,G81/$H$48)) -> 0 | I81: =SUM(EMP_1!I81+EMP_2!I81) -> 0 | J81: =IF($J$48="ERRO","ERRO",IF($J$48=0,0,I81/$J$48)) -> 0
B82: Leasing | C82: =SUM(EMP_1!C82+EMP_2!C82) -> 0 | D82: =IF($D$48="ERRO","ERRO",IF($D$48=0,0,C82/$D$48)) -> 0 | E82: =SUM(EMP_1!E82+EMP_2!E82) -> 0 | F82: =IF($F$48="ERRO","ERRO",IF($F$48=0,0,E82/$F$48)) -> 0 | G82: =SUM(EMP_1!G82+EMP_2!G82) -> 0 | H82: =IF($H$48="ERRO","ERRO",IF($H$48=0,0,G82/$H$48)) -> 0 | I82: =SUM(EMP_1!I82+EMP_2!I82) -> 0 | J82: =IF($J$48="ERRO","ERRO",IF($J$48=0,0,I82/$J$48)) -> 0
B83: Financiamentos c/ Tradings | C83: =SUM(EMP_1!C83+EMP_2!C83) -> 0 | D83: =IF($D$48="ERRO","ERRO",IF($D$48=0,0,C83/$D$48)) -> 0 | E83: =SUM(EMP_1!E83+EMP_2!E83) -> 0 | F83: =IF($F$48="ERRO","ERRO",IF($F$48=0,0,E83/$F$48)) -> 0 | G83: =SUM(EMP_1!G83+EMP_2!G83) -> 0 | H83: =IF($H$48="ERRO","ERRO",IF($H$48=0,0,G83/$H$48)) -> 0 | I83: =SUM(EMP_1!I83+EMP_2!I83) -> 0 | J83: =IF($J$48="ERRO","ERRO",IF($J$48=0,0,I83/$J$48)) -> 0
B84: Securitização | C84: =SUM(EMP_1!C84+EMP_2!C84) -> 0 | D84: =IF($D$48="ERRO","ERRO",IF($D$48=0,0,C84/$D$48)) -> 0 | E84: =SUM(EMP_1!E84+EMP_2!E84) -> 0 | F84: =IF($F$48="ERRO","ERRO",IF($F$48=0,0,E84/$F$48)) -> 0 | G84: =SUM(EMP_1!G84+EMP_2!G84) -> 0 | H84: =IF($H$48="ERRO","ERRO",IF($H$48=0,0,G84/$H$48)) -> 0 | I84: =SUM(EMP_1!I84+EMP_2!I84) -> 0 | J84: =IF($J$48="ERRO","ERRO",IF($J$48=0,0,I84/$J$48)) -> 0
B85: Custo Orçado | C85: =SUM(EMP_1!C85+EMP_2!C85) -> 0 | D85: =IF($D$48="ERRO","ERRO",IF($D$48=0,0,C85/$D$48)) -> 0 | E85: =SUM(EMP_1!E85+EMP_2!E85) -> 0 | F85: =IF($F$48="ERRO","ERRO",IF($F$48=0,0,E85/$F$48)) -> 0 | G85: =SUM(EMP_1!G85+EMP_2!G85) -> 0 | H85: =IF($H$48="ERRO","ERRO",IF($H$48=0,0,G85/$H$48)) -> 0 | I85: =SUM(EMP_1!I85+EMP_2!I85) -> 0 | J85: =IF($J$48="ERRO","ERRO",IF($J$48=0,0,I85/$J$48)) -> 0
B86: Terrenos | C86: =SUM(EMP_1!C86+EMP_2!C86) -> 0 | D86: =IF($D$48="ERRO","ERRO",IF($D$48=0,0,C86/$D$48)) -> 0 | E86: =SUM(EMP_1!E86+EMP_2!E86) -> 0 | F86: =IF($F$48="ERRO","ERRO",IF($F$48=0,0,E86/$F$48)) -> 0 | G86: =SUM(EMP_1!G86+EMP_2!G86) -> 0 | H86: =IF($H$48="ERRO","ERRO",IF($H$48=0,0,G86/$H$48)) -> 0 | I86: =SUM(EMP_1!I86+EMP_2!I86) -> 0 | J86: =IF($J$48="ERRO","ERRO",IF($J$48=0,0,I86/$J$48)) -> 0
B87: Outorga | C87: =SUM(EMP_1!C87+EMP_2!C87) -> 0 | D87: =IF($D$48="ERRO","ERRO",IF($D$48=0,0,C87/$D$48)) -> 0 | E87: =SUM(EMP_1!E87+EMP_2!E87) -> 0 | F87: =IF($F$48="ERRO","ERRO",IF($F$48=0,0,E87/$F$48)) -> 0 | G87: =SUM(EMP_1!G87+EMP_2!G87) -> 0 | H87: =IF($H$48="ERRO","ERRO",IF($H$48=0,0,G87/$H$48)) -> 0 | I87: =SUM(EMP_1!I87+EMP_2!I87) -> 0 | J87: =IF($J$48="ERRO","ERRO",IF($J$48=0,0,I87/$J$48)) -> 0
B88: Compromissos Consorciados | C88: =SUM(EMP_1!C88+EMP_2!C88) -> 0 | D88: =IF($D$48="ERRO","ERRO",IF($D$48=0,0,C88/$D$48)) -> 0 | E88: =SUM(EMP_1!E88+EMP_2!E88) -> 0 | F88: =IF($F$48="ERRO","ERRO",IF($F$48=0,0,E88/$F$48)) -> 0 | G88: =SUM(EMP_1!G88+EMP_2!G88) -> 0 | H88: =IF($H$48="ERRO","ERRO",IF($H$48=0,0,G88/$H$48)) -> 0 | I88: =SUM(EMP_1!I88+EMP_2!I88) -> 0 | J88: =IF($J$48="ERRO","ERRO",IF($J$48=0,0,I88/$J$48)) -> 0
B89: Plano de Previdênciário | C89: =SUM(EMP_1!C89+EMP_2!C89) -> 0 | D89: =IF($D$48="ERRO","ERRO",IF($D$48=0,0,C89/$D$48)) -> 0 | E89: =SUM(EMP_1!E89+EMP_2!E89) -> 0 | F89: =IF($F$48="ERRO","ERRO",IF($F$48=0,0,E89/$F$48)) -> 0 | G89: =SUM(EMP_1!G89+EMP_2!G89) -> 0 | H89: =IF($H$48="ERRO","ERRO",IF($H$48=0,0,G89/$H$48)) -> 0 | I89: =SUM(EMP_1!I89+EMP_2!I89) -> 0 | J89: =IF($J$48="ERRO","ERRO",IF($J$48=0,0,I89/$J$48)) -> 0
B90: Dividendos a pagar | C90: =SUM(EMP_1!C90+EMP_2!C90) -> 0 | D90: =IF($D$48="ERRO","ERRO",IF($D$48=0,0,C90/$D$48)) -> 0 | E90: =SUM(EMP_1!E90+EMP_2!E90) -> 0 | F90: =IF($F$48="ERRO","ERRO",IF($F$48=0,0,E90/$F$48)) -> 0 | G90: =SUM(EMP_1!G90+EMP_2!G90) -> 0 | H90: =IF($H$48="ERRO","ERRO",IF($H$48=0,0,G90/$H$48)) -> 0 | I90: =SUM(EMP_1!I90+EMP_2!I90) -> 0 | J90: =IF($J$48="ERRO","ERRO",IF($J$48=0,0,I90/$J$48)) -> 0
B91: Provisão para Contingência | C91: =SUM(EMP_1!C91+EMP_2!C91) -> 0 | D91: =IF($D$48="ERRO","ERRO",IF($D$48=0,0,C91/$D$48)) -> 0 | E91: =SUM(EMP_1!E91+EMP_2!E91) -> 0 | F91: =IF($F$48="ERRO","ERRO",IF($F$48=0,0,E91/$F$48)) -> 0 | G91: =SUM(EMP_1!G91+EMP_2!G91) -> 0 | H91: =IF($H$48="ERRO","ERRO",IF($H$48=0,0,G91/$H$48)) -> 0 | I91: =SUM(EMP_1!I91+EMP_2!I91) -> 0 | J91: =IF($J$48="ERRO","ERRO",IF($J$48=0,0,I91/$J$48)) -> 0
... B95: Outros Nao Operac. | C95: =SUM(EMP_1!C95+EMP_2!C95) -> 0 | D95: =IF($D$48="ERRO","ERRO",IF($D$48=0,0,C95/$D$48)) -> 0 | E95: =SUM(EMP_1!E95+EMP_2!E95) -> 0 | F95: =IF($F$48="ERRO","ERRO",IF($F$48=0,0,E95/$F$48)) -> 0 | G95: =SUM(EMP_1!G95+EMP_2!G95) -> 0 | H95: =IF($H$48="ERRO","ERRO",IF($H$48=0,0,G95/$H$48)) -> 0 | I95: =SUM(EMP_1!I95+EMP_2!I95) -> 0 | J95: =IF($J$48="ERRO","ERRO",IF($J$48=0,0,I95/$J$48)) -> 0
B97: RES. EXERC. FUT. | C97: 0 | D97: =IF($D$48="ERRO","ERRO",IF($D$48=0,0,C97/$D$48)) -> 0 | E97: 0 | F97: =IF($F$48="ERRO","ERRO",IF($F$48=0,0,E97/$F$48)) -> 0 | G97: 0 | H97: =IF($H$48="ERRO","ERRO",IF($H$48=0,0,G97/$H$48)) -> 0 | I97: 0 | J97: =IF($J$48="ERRO","ERRO",IF($J$48=0,0,I97/$J$48)) -> 0
B99: PARTIC. MINORIT. | C99: 0 | D99: =IF($D$48="ERRO","ERRO",IF($D$48=0,0,C99/$D$48)) -> 0 | E99: 0 | F99: =IF($F$48="ERRO","ERRO",IF($F$48=0,0,E99/$F$48)) -> 0 | G99: 0 | H99: =IF($H$48="ERRO","ERRO",IF($H$48=0,0,G99/$H$48)) -> 0 | I99: 0 | J99: =IF($J$48="ERRO","ERRO",IF($J$48=0,0,I99/$J$48)) -> 0
B101: PATRIMÔNIO LÍQUIDO | C101: =SUM(EMP_1!C101+EMP_2!C101) -> 0 | D101: =IF($D$48="ERRO","ERRO",IF($D$48=0,0,C101/$D$48)) -> 0 | E101: =SUM(EMP_1!E101+EMP_2!E101) -> 0 | F101: =IF($F$48="ERRO","ERRO",IF($F$48=0,0,E101/$F$48)) -> 0 | G101: =SUM(EMP_1!G101+EMP_2!G101) -> 0 | H101: =IF($H$48="ERRO","ERRO",IF($H$48=0,0,G101/$H$48)) -> 0 | I101: =SUM(EMP_1!I101+EMP_2!I101) -> 0 | J101: =IF($J$48="ERRO","ERRO",IF($J$48=0,0,I101/$J$48)) -> 0
B102: Capital e Reservas | C102: =C101-C103-C104 -> 0 | D102: =IF($D$48="ERRO","ERRO",IF($D$48=0,0,C102/$D$48)) -> 0 | E102: =E101-E103-E104 -> 0 | F102: =IF($F$48="ERRO","ERRO",IF($F$48=0,0,E102/$F$48)) -> 0 | G102: =G101-G103-G104 -> 0 | H102: =IF($H$48="ERRO","ERRO",IF($H$48=0,0,G102/$H$48)) -> 0 | I102: =I101-I103-I104 -> 0 | J102: =IF($J$48="ERRO","ERRO",IF($J$48=0,0,I102/$J$48)) -> 0
B103: Reservas de Reavaliação | D103: =IF($D$48="ERRO","ERRO",IF($D$48=0,0,C103/$D$48)) -> 0 | F103: =IF($F$48="ERRO","ERRO",IF($F$48=0,0,E103/$F$48)) -> 0 | H103: =IF($H$48="ERRO","ERRO",IF($H$48=0,0,G103/$H$48)) -> 0 | J103: =IF($J$48="ERRO","ERRO",IF($J$48=0,0,I103/$J$48)) -> 0
B104: Resultado do Período | C104: =C139 -> 0 | D104: =IF($D$48="ERRO","ERRO",IF($D$48=0,0,C104/$D$48)) -> 0 | E104: =E139 -> 0 | F104: =IF($F$48="ERRO","ERRO",IF($F$48=0,0,E104/$F$48)) -> 0 | G104: =G139 -> 0 | H104: =IF($H$48="ERRO","ERRO",IF($H$48=0,0,G104/$H$48)) -> 0 | I104: =I139 -> 0 | J104: =IF($J$48="ERRO","ERRO",IF($J$48=0,0,I104/$J$48)) -> 0
B106: DEMONSTRATIVO DE RESULTADOS
C107: JAN/2022-DEZ/2022 | E107: JAN/2023-DEZ/2023 | G107: JAN/2024-DEZ/2024 | I107: JAN/2025-DEZ/2025
B108: N° MESES DO PERIODO | C108: 12 | E108: 12 | G108: 12 | I108: 12
C109: R$MIL | D109: (%) | E109: R$MIL | F109: (%) | G109: R$MIL | H109: (%) | I109: R$MIL | J109: (%)
B111: FATUR. BRUTO | C111: =SUM(EMP_1!C111+EMP_2!C111) -> 0 | D111: =IF($D$114=0,0,C111/$D$114) -> 0 | E111: =SUM(EMP_1!E111+EMP_2!E111) -> 0 | F111: =IF($F$114=0,0,E111/$F$114) -> 0 | G111: =SUM(EMP_1!G111+EMP_2!G111) -> 0 | H111: =IF($H$114=0,0,G111/$H$114) -> 0 | I111: =SUM(EMP_1!I111+EMP_2!I111) -> 0 | J111: =IF($J$114=0,0,I111/$J$114) -> 0
B112: Impostos/Deduções | C112: =SUM(EMP_1!C112+EMP_2!C112) -> 0 | D112: =IF($D$114=0,0,C112/$D$114) -> 0 | E112: =SUM(EMP_1!E112+EMP_2!E112) -> 0 | F112: =IF($F$114=0,0,E112/$F$114) -> 0 | G112: =SUM(EMP_1!G112+EMP_2!G112) -> 0 | H112: =IF($H$114=0,0,G112/$H$114) -> 0 | I112: =SUM(EMP_1!I112+EMP_2!I112) -> 0 | J112: =IF($J$114=0,0,I112/$J$114) -> 0
B113: FATUR. LÍQUIDO | C113: =C111-C112 -> 0 | D113: =IF($D$114=0,0,C113/$D$114) -> 0 | E113: =E111-E112 -> 0 | F113: =IF($F$114=0,0,E113/$F$114) -> 0 | G113: =G111-G112 -> 0 | H113: =IF($H$114=0,0,G113/$H$114) -> 0 | I113: =I111-I112 -> 0 | J113: =IF($J$114=0,0,I113/$J$114) -> 0
B114: Custos | C114: =SUM(C115:C118) -> 0 | D114: =IF($D$114=0,0,C114/$D$114) -> 0 | E114: =SUM(E115:E118) -> 0 | F114: =IF($F$114=0,0,E114/$F$114) -> 0 | G114: =SUM(G115:G118) -> 0 | H114: =IF($H$114=0,0,G114/$H$114) -> 0 | I114: =SUM(I115:I118) -> 0 | J114: =IF($J$114=0,0,I114/$J$114) -> 0
B115: - Depreciação/Amortização | C115: =SUM(EMP_1!C115+EMP_2!C115) -> 0 | D115: =IF($D$114=0,0,C115/$D$114) -> 0 | E115: =SUM(EMP_1!E115+EMP_2!E115) -> 0 | F115: =IF($F$114=0,0,E115/$F$114) -> 0 | G115: =SUM(EMP_1!G115+EMP_2!G115) -> 0 | H115: =IF($H$114=0,0,G115/$H$114) -> 0 | I115: =SUM(EMP_1!I115+EMP_2!I115) -> 0 | J115: =IF($J$114=0,0,I115/$J$114) -> 0
B116: - Depreciação/Amortização Estimada | C116: =SUM(EMP_1!C116+EMP_2!C116) -> 0 | D116: =IF($D$114=0,0,C116/$D$114) -> 0 | E116: =SUM(EMP_1!E116+EMP_2!E116) -> 0 | F116: =IF($F$114=0,0,E116/$F$114) -> 0 | G116: =SUM(EMP_1!G116+EMP_2!G116) -> 0 | H116: =IF($H$114=0,0,G116/$H$114) -> 0 | I116: =SUM(EMP_1!I116+EMP_2!I116) -> 0 | J116: =IF($J$114=0,0,I116/$J$114) -> 0
B117: - Arrendamento Mercantil | C117: =SUM(EMP_1!C117+EMP_2!C117) -> 0 | D117: =IF($D$114=0,0,C117/$D$114) -> 0 | E117: =SUM(EMP_1!E117+EMP_2!E117) -> 0 | F117: =IF($F$114=0,0,E117/$F$114) -> 0 | G117: =SUM(EMP_1!G117+EMP_2!G117) -> 0 | H117: =IF($H$114=0,0,G117/$H$114) -> 0 | I117: =SUM(EMP_1!I117+EMP_2!I117) -> 0 | J117: =IF($J$114=0,0,I117/$J$114) -> 0
B118: - Custos Diretos | C118: =SUM(EMP_1!C118+EMP_2!C118) -> 0 | D118: =IF($D$114=0,0,C118/$D$114) -> 0 | E118: =SUM(EMP_1!E118+EMP_2!E118) -> 0 | F118: =IF($F$114=0,0,E118/$F$114) -> 0 | G118: =SUM(EMP_1!G118+EMP_2!G118) -> 0 | H118: =IF($H$114=0,0,G118/$H$114) -> 0 | I118: =SUM(EMP_1!I118+EMP_2!I118) -> 0 | J118: =IF($J$114=0,0,I118/$J$114) -> 0
B119: RES. BRUTO | C119: =C113-C114 -> 0 | D119: =IF($D$114=0,0,C119/$D$114) -> 0 | E119: =E113-E114 -> 0 | F119: =IF($F$114=0,0,E119/$F$114) -> 0 | G119: =G113-G114 -> 0 | H119: =IF($H$114=0,0,G119/$H$114) -> 0 | I119: =I113-I114 -> 0 | J119: =IF($J$114=0,0,I119/$J$114) -> 0
B120: Desps. Operac. | C120: =SUM(C121:C123) -> 0 | D120: =IF($D$114=0,0,C120/$D$114) -> 0 | E120: =SUM(E121:E123) -> 0 | F120: =IF($F$114=0,0,E120/$F$114) -> 0 | G120: =SUM(G121:G123) -> 0 | H120: =IF($H$114=0,0,G120/$H$114) -> 0 | I120: =SUM(I121:I123) -> 0 | J120: =IF($J$114=0,0,I120/$J$114) -> 0
B121: -Despesas Comerciais | C121: =SUM(EMP_1!C121+EMP_2!C121) -> 0 | D121: =IF($D$114=0,0,C121/$D$114) -> 0 | E121: =SUM(EMP_1!E121+EMP_2!E121) -> 0 | F121: =IF($F$114=0,0,E121/$F$114) -> 0 | G121: =SUM(EMP_1!G121+EMP_2!G121) -> 0 | H121: =IF($H$114=0,0,G121/$H$114) -> 0 | I121: =SUM(EMP_1!I121+EMP_2!I121) -> 0 | J121: =IF($J$114=0,0,I121/$J$114) -> 0
B122: -Despesas Administrativas | C122: =SUM(EMP_1!C122+EMP_2!C122) -> 0 | D122: =IF($D$114=0,0,C122/$D$114) -> 0 | E122: =SUM(EMP_1!E122+EMP_2!E122) -> 0 | F122: =IF($F$114=0,0,E122/$F$114) -> 0 | G122: =SUM(EMP_1!G122+EMP_2!G122) -> 0 | H122: =IF($H$114=0,0,G122/$H$114) -> 0 | I122: =SUM(EMP_1!I122+EMP_2!I122) -> 0 | J122: =IF($J$114=0,0,I122/$J$114) -> 0
B123: -Despesas c/ Depreciação | C123: =SUM(EMP_1!C123+EMP_2!C123) -> 0 | D123: =IF($D$114=0,0,C123/$D$114) -> 0 | E123: =SUM(EMP_1!E123+EMP_2!E123) -> 0 | F123: =IF($F$114=0,0,E123/$F$114) -> 0 | G123: =SUM(EMP_1!G123+EMP_2!G123) -> 0 | H123: =IF($H$114=0,0,G123/$H$114) -> 0 | I123: =SUM(EMP_1!I123+EMP_2!I123) -> 0 | J123: =IF($J$114=0,0,I123/$J$114) -> 0
B124: RES. ATIVIDADE | C124: =C119-C120 -> 0 | D124: =IF($D$114=0,0,C124/$D$114) -> 0 | E124: =E119-E120 -> 0 | F124: =IF($F$114=0,0,E124/$F$114) -> 0 | G124: =G119-G120 -> 0 | H124: =IF($H$114=0,0,G124/$H$114) -> 0 | I124: =I119-I120 -> 0 | J124: =IF($J$114=0,0,I124/$J$114) -> 0
B125: Despesas/(Receitas) Financ. Líq. | C125: =SUM(C126:C127) -> 0 | D125: =IF($D$114=0,0,C125/$D$114) -> 0 | E125: =SUM(E126:E127) -> 0 | F125: =IF($F$114=0,0,E125/$F$114) -> 0 | G125: =SUM(G126:G127) -> 0 | H125: =IF($H$114=0,0,G125/$H$114) -> 0 | I125: =SUM(I126:I127) -> 0 | J125: =IF($J$114=0,0,I125/$J$114) -> 0
B126: - Despesas Financeiras | C126: =SUM(EMP_1!C126+EMP_2!C126) -> 0 | D126: =IF($D$114=0,0,C126/$D$114) -> 0 | E126: =SUM(EMP_1!E126+EMP_2!E126) -> 0 | F126: =IF($F$114=0,0,E126/$F$114) -> 0 | G126: =SUM(EMP_1!G126+EMP_2!G126) -> 0 | H126: =IF($H$114=0,0,G126/$H$114) -> 0 | I126: =SUM(EMP_1!I126+EMP_2!I126) -> 0 | J126: =IF($J$114=0,0,I126/$J$114) -> 0
B127: - Receitas Financeiras | C127: =SUM(EMP_1!C127+EMP_2!C127) -> 0 | D127: =IF($D$114=0,0,C127/$D$114) -> 0 | E127: =SUM(EMP_1!E127+EMP_2!E127) -> 0 | F127: =IF($F$114=0,0,E127/$F$114) -> 0 | G127: =SUM(EMP_1!G127+EMP_2!G127) -> 0 | H127: =IF($H$114=0,0,G127/$H$114) -> 0 | I127: =SUM(EMP_1!I127+EMP_2!I127) -> 0 | J127: =IF($J$114=0,0,I127/$J$114) -> 0
B128: Variações Monetárias Líq. LP | C128: =SUM(EMP_1!C128+EMP_2!C128) -> 0 | D128: =IF($D$114=0,0,C128/$D$114) -> 0 | E128: =SUM(EMP_1!E128+EMP_2!E128) -> 0 | F128: =IF($F$114=0,0,E128/$F$114) -> 0 | G128: =SUM(EMP_1!G128+EMP_2!G128) -> 0 | H128: =IF($H$114=0,0,G128/$H$114) -> 0 | I128: =SUM(EMP_1!I128+EMP_2!I128) -> 0 | J128: =IF($J$114=0,0,I128/$J$114) -> 0
B129: Outras Rec./(Desp.) Operac. | C129: =SUM(EMP_1!C129+EMP_2!C129) -> 0 | D129: =IF($D$114=0,0,C129/$D$114) -> 0 | E129: =SUM(EMP_1!E129+EMP_2!E129) -> 0 | F129: =IF($F$114=0,0,E129/$F$114) -> 0 | G129: =SUM(EMP_1!G129+EMP_2!G129) -> 0 | H129: =IF($H$114=0,0,G129/$H$114) -> 0 | I129: =SUM(EMP_1!I129+EMP_2!I129) -> 0 | J129: =IF($J$114=0,0,I129/$J$114) -> 0
B130: RES. OPERACIONAL | C130: =C124-C125+C128+C129 -> 0 | D130: =IF($D$114=0,0,C130/$D$114) -> 0 | E130: =E124-E125+E128+E129 -> 0 | F130: =IF($F$114=0,0,E130/$F$114) -> 0 | G130: =G124-G125+G128+G129 -> 0 | H130: =IF($H$114=0,0,G130/$H$114) -> 0 | I130: =I124-I125+I128+I129 -> 0 | J130: =IF($J$114=0,0,I130/$J$114) -> 0
...

Sheet HIGHLIGHTS
B1: 44896 | C1: A.V. % | D1: 45261 | E1: A.V. % | F1: 45627 | G1: A.V. % | H1: 45992 | I1: A.V. %
A2: RECEITA BRUTA | B2: =CONSOLIDADO!C111 -> 0 | C2: =B2/$B$2 -> #DIV/0! | D2: =CONSOLIDADO!E111 -> 0 | E2: =D2/$D$2 -> #DIV/0! | F2: =CONSOLIDADO!G111 -> 0 | G2: =F2/$F$2 -> #DIV/0! | H2: =CONSOLIDADO!I111 -> 0 | I2: =H2/$H$2 -> #DIV/0!
A3: RECEITA LÍQUIDA | B3: =CONSOLIDADO!C113 -> 0 | C3: =B3/$B$2 -> #DIV/0! | D3: =CONSOLIDADO!E113 -> 0 | E3: =D3/$D$2 -> #DIV/0! | F3: =CONSOLIDADO!G113 -> 0 | G3: =F3/$F$2 -> #DIV/0! | H3: =CONSOLIDADO!I113 -> 0 | I3: =H3/$H$2 -> #DIV/0!
A4: RESULTADO BRUTO | B4: =CONSOLIDADO!C119 -> 0 | C4: =B4/$B$2 -> #DIV/0! | D4: =CONSOLIDADO!E119 -> 0 | E4: =D4/$D$2 -> #DIV/0! | F4: =CONSOLIDADO!G119 -> 0 | G4: =F4/$F$2 -> #DIV/0! | H4: =CONSOLIDADO!I119 -> 0 | I4: =H4/$H$2 -> #DIV/0!
A5: RESULTADO ATIVIDADE | B5: =CONSOLIDADO!C124 -> 0 | C5: =B5/$B$2 -> #DIV/0! | D5: =CONSOLIDADO!E124 -> 0 | E5: =D5/$D$2 -> #DIV/0! | F5: =CONSOLIDADO!G124 -> 0 | G5: =F5/$F$2 -> #DIV/0! | H5: =CONSOLIDADO!I124 -> 0 | I5: =H5/$H$2 -> #DIV/0!
A6: RESULTADO LÍQUIDO | B6: =CONSOLIDADO!C139 -> 0 | C6: =B6/$B$2 -> #DIV/0! | D6: =CONSOLIDADO!E139 -> 0 | E6: =D6/$D$2 -> #DIV/0! | F6: =CONSOLIDADO!G139 -> 0 | G6: =F6/$F$2 -> #DIV/0! | H6: =CONSOLIDADO!I139 -> 0 | I6: =H6/$H$2 -> #DIV/0!
A7: DESPESA FINANCEIRA LÍQ. | B7: =CONSOLIDADO!C125 -> 0 | C7: =B7/$B$2 -> #DIV/0! | D7: =CONSOLIDADO!E125 -> 0 | E7: =D7/$D$2 -> #DIV/0! | F7: =CONSOLIDADO!G125 -> 0 | G7: =F7/$F$2 -> #DIV/0! | H7: =CONSOLIDADO!I125 -> 0 | I7: =H7/$H$2 -> #DIV/0!
A8: RESULTADO OPERACIONAL | B8: =CONSOLIDADO!C130 -> 0 | C8: =B8/$B$2 -> #DIV/0! | D8: =CONSOLIDADO!E130 -> 0 | E8: =D8/$D$2 -> #DIV/0! | F8: =CONSOLIDADO!G130 -> 0 | G8: =F8/$F$2 -> #DIV/0! | H8: =CONSOLIDADO!I130 -> 0 | I8: =H8/$H$2 -> #DIV/0!
A9: EBITDA | B9: =CONSOLIDADO!C157 -> 0 | C9: =B9/$B$2 -> #DIV/0! | D9: =CONSOLIDADO!E157 -> 0 | E9: =D9/$D$2 -> #DIV/0! | F9: =CONSOLIDADO!G157 -> 0 | G9: =F9/$F$2 -> #DIV/0! | H9: =CONSOLIDADO!I157 -> 0 | I9: =H9/$H$2 -> #DIV/0!
A10: GERAÇÃO DE CAIXA APÓS DF | B10: =CONSOLIDADO!C157-CONSOLIDADO!C125 -> 0 | C10: =B10/$B$2 -> #DIV/0! | D10: =CONSOLIDADO!E157-CONSOLIDADO!E125 -> 0 | E10: =D10/$D$2 -> #DIV/0! | F10: =CONSOLIDADO!G157-CONSOLIDADO!G125 -> 0 | G10: =F10/$F$2 -> #DIV/0! | H10: =CONSOLIDADO!I157-CONSOLIDADO!I125 -> 0 | I10: =H10/$H$2 -> #DIV/0!
B12: 44896 | C12: 45261 | D12: VAR. | E12: 45627 | F12: VAR. | G12: 45992 | H12: VAR.
A13: CONTAS A RECEBER | B13: =CONSOLIDADO!C14 -> 0 | C13: =CONSOLIDADO!E14 -> 0 | D13: =C13/B13-1 -> #DIV/0! | E13: =CONSOLIDADO!G14 -> 0 | F13: =E13/C13-1 -> #DIV/0! | G13: =CONSOLIDADO!I14 -> 0 | H13: =G13/E13-1 -> #DIV/0!
A14: ESTOQUE | B14: =CONSOLIDADO!C17 -> 0 | C14: =CONSOLIDADO!E17 -> 0 | D14: =C14/B14-1 -> #DIV/0! | E14: =CONSOLIDADO!G17 -> 0 | F14: =E14/C14-1 -> #DIV/0! | G14: =CONSOLIDADO!I17 -> 0 | H14: =G14/E14-1 -> #DIV/0!
A15: IMOBILIZADO | B15: =CONSOLIDADO!C43 -> 0 | C15: =CONSOLIDADO!E43 -> 0 | D15: =C15/B15-1 -> #DIV/0! | E15: =CONSOLIDADO!G43 -> 0 | F15: =E15/C15-1 -> #DIV/0! | G15: =CONSOLIDADO!I43 -> 0 | H15: =G15/E15-1 -> #DIV/0!
A16: FORNECEDORES | B16: =CONSOLIDADO!C52+CONSOLIDADO!C53 -> 0 | C16: =CONSOLIDADO!E52+CONSOLIDADO!E53 -> 0 | D16: =C16/B16-1 -> #DIV/0! | E16: =CONSOLIDADO!G52+CONSOLIDADO!G53 -> 0 | F16: =E16/C16-1 -> #DIV/0! | G16: =CONSOLIDADO!I52+CONSOLIDADO!I53 -> 0 | H16: =G16/E16-1 -> #DIV/0!
A17: DISPONIBILIDADE | B17: =CONSOLIDADO!C12+CONSOLIDADO!C13 -> 0 | C17: =CONSOLIDADO!E12+CONSOLIDADO!E13 -> 0 | D17: =C17/B17-1 -> #DIV/0! | E17: =CONSOLIDADO!G12+CONSOLIDADO!G13 -> 0 | F17: =E17/C17-1 -> #DIV/0! | G17: =CONSOLIDADO!I12+CONSOLIDADO!I13 -> 0 | H17: =G17/E17-1 -> #DIV/0!
A18: DÍVIDA TOTAL | B18: =CONSOLIDADO!C148 -> 0 | C18: =CONSOLIDADO!E148 -> 0 | D18: =C18/B18-1 -> #DIV/0! | E18: =CONSOLIDADO!G148 -> 0 | F18: =E18/C18-1 -> #DIV/0! | G18: =CONSOLIDADO!I148 -> 0 | H18: =G18/E18-1 -> #DIV/0!
A19: CURTO PRAZO | B19: =CONSOLIDADO!C146 -> 0 | C19: =CONSOLIDADO!E146 -> 0 | D19: =C19/B19-1 -> #DIV/0! | E19: =CONSOLIDADO!G146 -> 0 | F19: =E19/C19-1 -> #DIV/0! | G19: =CONSOLIDADO!I146 -> 0 | H19: =G19/E19-1 -> #DIV/0!
A20: LONGO PRAZO | B20: =CONSOLIDADO!C147 -> 0 | C20: =CONSOLIDADO!E147 -> 0 | D20: =C20/B20-1 -> #DIV/0! | E20: =CONSOLIDADO!G147 -> 0 | F20: =E20/C20-1 -> #DIV/0! | G20: =CONSOLIDADO!I147 -> 0 | H20: =G20/E20-1 -> #DIV/0!
A21: DÍVIDA LÍQUIDA | B21: =CONSOLIDADO!C145 -> 0 | C21: =CONSOLIDADO!E145 -> 0 | D21: =C21/B21-1 -> #DIV/0! | E21: =CONSOLIDADO!G145 -> 0 | F21: =E21/C21-1 -> #DIV/0! | G21: =CONSOLIDADO!I145 -> 0 | H21: =G21/E21-1 -> #DIV/0!
A22: ATIVO CIRCULANTE | B22: =CONSOLIDADO!C11 -> 0 | C22: =CONSOLIDADO!E11 -> 0 | D22: =C22/B22-1 -> #DIV/0! | E22: =CONSOLIDADO!G11 -> 0 | F22: =E22/C22-1 -> #DIV/0! | G22: =CONSOLIDADO!I11 -> 0 | H22: =G22/E22-1 -> #DIV/0!
A23: PATRIMONIO LÍQUIDO | B23: =CONSOLIDADO!C101 -> 0 | C23: =CONSOLIDADO!E101 -> 0 | D23: =C23/B23-1 -> #DIV/0! | E23: =CONSOLIDADO!G101 -> 0 | F23: =E23/C23-1 -> #DIV/0! | G23: =CONSOLIDADO!I101 -> 0 | H23: =G23/E23-1 -> #DIV/0!
A24: DÍVIDA LÍQUIDA/EBITDA | B24: =CONSOLIDADO!C160 -> N/A | C24: =CONSOLIDADO!E160 -> N/A | E24: =CONSOLIDADO!G160 -> N/A | G24: =CONSOLIDADO!I160 -> N/A
